<document>
    <url>
        http://www.stsci.edu/hst/observatory/cdbs/SIfileInfo/WFPC2/2003darks
    </url>
    <table>
        <tr><th>File</th><th>Mode</th><th>Clock</th><th>Gain</th><th>Use After</th><th>Pedigree</th><th>Delivery #</th><th>Delivery Date</th><th>OTFR Start Date</th><th>Comments</th></tr>
        <tr><td><a href="http://archive.stsci.edu/cgi-bin/dataset_lookup?dataset_input_list=o191016bu*">o191016bu.r3h</a></td><td>FULL</td><td>OFF</td><td>7</td><td>Dec 31 2003  06:30AM</td><td>INFLIGHT</td><td>11320</td><td>Jan 12 2004  03:20PM</td><td>2004/01/13</td><td>Pipeline dark: 120 frame superdark with hotpixels from 31/12/2003</td></tr>
        <tr><td><a href="http://archive.stsci.edu/cgi-bin/dataset_lookup?dataset_input_list=o191016cu*">o191016cu.r3h</a></td><td>FULL</td><td>ON</td><td>7</td><td>Dec 31 2003  06:30AM</td><td>INFLIGHT</td><td>11320</td><td>Jan 12 2004  03:20PM</td><td>2004/01/13</td><td>Pipeline dark: 120 frame superdark with hotpixels from 31/12/2003</td></tr>
        <tr><td><a href="http://archive.stsci.edu/cgi-bin/dataset_lookup?dataset_input_list=o1910169u*">o1910169u.r3h</a></td><td>FULL</td><td>OFF</td><td>15</td><td>Dec 31 2003  06:30AM</td><td>INFLIGHT</td><td>11320</td><td>Jan 12 2004  03:20PM</td><td>2004/01/13</td><td>Pipeline dark: 120 frame superdark with hotpixels from 31/12/2003</td></tr>
        <tr><td><a href="http://archive.stsci.edu/cgi-bin/dataset_lookup?dataset_input_list=o191016au*">o191016au.r3h</a></td><td>FULL</td><td>ON</td><td>15</td><td>Dec 31 2003  06:30AM</td><td>INFLIGHT</td><td>11320</td><td>Jan 12 2004  03:20PM</td><td>2004/01/13</td><td>Pipeline dark: 120 frame superdark with hotpixels from 31/12/2003</td></tr>
        <tr><td><a href="http://archive.stsci.edu/cgi-bin/dataset_lookup?dataset_input_list=ncu15386u*">ncu15386u.r3h</a></td><td>FULL</td><td>OFF</td><td>7</td><td>Dec 22 2003  05:01AM</td><td>INFLIGHT</td><td>11315</td><td>Jan 05 2004  03:31PM</td><td>2004/01/05</td><td>Pipeline dark: 120 frame superdark with hotpixels from 22/12/2003</td></tr>
        <tr><td><a href="http://archive.stsci.edu/cgi-bin/dataset_lookup?dataset_input_list=ncu15387u*">ncu15387u.r3h</a></td><td>FULL</td><td>ON</td><td>7</td><td>Dec 22 2003  05:01AM</td><td>INFLIGHT</td><td>11315</td><td>Jan 05 2004  03:31PM</td><td>2004/01/05</td><td>Pipeline dark: 120 frame superdark with hotpixels from 22/12/2003</td></tr>
        <tr><td><a href="http://archive.stsci.edu/cgi-bin/dataset_lookup?dataset_input_list=ncu15384u*">ncu15384u.r3h</a></td><td>FULL</td><td>OFF</td><td>15</td><td>Dec 22 2003  05:01AM</td><td>INFLIGHT</td><td>11315</td><td>Jan 05 2004  03:31PM</td><td>2004/01/05</td><td>Pipeline dark: 120 frame superdark with hotpixels from 22/12/2003</td></tr>
        <tr><td><a href="http://archive.stsci.edu/cgi-bin/dataset_lookup?dataset_input_list=ncu15385u*">ncu15385u.r3h</a></td><td>FULL</td><td>ON</td><td>15</td><td>Dec 22 2003  05:01AM</td><td>INFLIGHT</td><td>11315</td><td>Jan 05 2004  03:31PM</td><td>2004/01/05</td><td>Pipeline dark: 120 frame superdark with hotpixels from 22/12/2003</td></tr>
        <tr><td><a href="http://archive.stsci.edu/cgi-bin/dataset_lookup?dataset_input_list=ncm14306u*">ncm14306u.r3h</a></td><td>FULL</td><td>OFF</td><td>7</td><td>Dec 15 2003  03:22AM</td><td>INFLIGHT</td><td>11312</td><td>Dec 23 2003  01:01PM</td><td>2003/12/23</td><td>Pipeline dark: 120 frame superdark with hotpixels from 15/12/2003</td></tr>
        <tr><td><a href="http://archive.stsci.edu/cgi-bin/dataset_lookup?dataset_input_list=ncm14307u*">ncm14307u.r3h</a></td><td>FULL</td><td>ON</td><td>7</td><td>Dec 15 2003  03:22AM</td><td>INFLIGHT</td><td>11312</td><td>Dec 23 2003  01:01PM</td><td>2003/12/23</td><td>Pipeline dark: 120 frame superdark with hotpixels from 15/12/2003</td></tr>
        <tr><td><a href="http://archive.stsci.edu/cgi-bin/dataset_lookup?dataset_input_list=ncm14304u*">ncm14304u.r3h</a></td><td>FULL</td><td>OFF</td><td>15</td><td>Dec 15 2003  03:22AM</td><td>INFLIGHT</td><td>11312</td><td>Dec 23 2003  01:01PM</td><td>2003/12/23</td><td>Pipeline dark: 120 frame superdark with hotpixels from 15/12/2003</td></tr>
        <tr><td><a href="http://archive.stsci.edu/cgi-bin/dataset_lookup?dataset_input_list=ncm14305u*">ncm14305u.r3h</a></td><td>FULL</td><td>ON</td><td>15</td><td>Dec 15 2003  03:22AM</td><td>INFLIGHT</td><td>11312</td><td>Dec 23 2003  01:01PM</td><td>2003/12/23</td><td>Pipeline dark: 120 frame superdark with hotpixels from 15/12/2003</td></tr>
        <tr><td><a href="http://archive.stsci.edu/cgi-bin/dataset_lookup?dataset_input_list=ncc1752eu*">ncc1752eu.r3h</a></td><td>FULL</td><td>OFF</td><td>7</td><td>Dec 08 2003  01:28PM</td><td>INFLIGHT</td><td>11302</td><td>Dec 15 2003  08:44PM</td><td>2003/12/16 15:38:00 US/Eastern</td><td>Pipeline dark: 120 frame superdark with hotpixels from 08/12/2003</td></tr>
        <tr><td><a href="http://archive.stsci.edu/cgi-bin/dataset_lookup?dataset_input_list=ncc1752fu*">ncc1752fu.r3h</a></td><td>FULL</td><td>ON</td><td>7</td><td>Dec 08 2003  01:28PM</td><td>INFLIGHT</td><td>11302</td><td>Dec 15 2003  08:44PM</td><td>2003/12/16 15:38:00 US/Eastern</td><td>Pipeline dark: 120 frame superdark with hotpixels from 08/12/2003</td></tr>
        <tr><td><a href="http://archive.stsci.edu/cgi-bin/dataset_lookup?dataset_input_list=ncc1752cu*">ncc1752cu.r3h</a></td><td>FULL</td><td>OFF</td><td>15</td><td>Dec 08 2003  01:28PM</td><td>INFLIGHT</td><td>11302</td><td>Dec 15 2003  08:44PM</td><td>2003/12/16 15:38:00 US/Eastern</td><td>Pipeline dark: 120 frame superdark with hotpixels from 08/12/2003</td></tr>
        <tr><td><a href="http://archive.stsci.edu/cgi-bin/dataset_lookup?dataset_input_list=ncc1752du*">ncc1752du.r3h</a></td><td>FULL</td><td>ON</td><td>15</td><td>Dec 08 2003  01:28PM</td><td>INFLIGHT</td><td>11302</td><td>Dec 15 2003  08:44PM</td><td>2003/12/16 15:38:00 US/Eastern</td><td>Pipeline dark: 120 frame superdark with hotpixels from 08/12/2003</td></tr>
        <tr><td><a href="http://archive.stsci.edu/cgi-bin/dataset_lookup?dataset_input_list=ncc17443u*">ncc17443u.r3h</a></td><td>FULL</td><td>OFF</td><td>7</td><td>Dec 01 2003  12:02AM</td><td>INFLIGHT</td><td>11302</td><td>Dec 15 2003  08:44PM</td><td>2003/12/16 15:38:00 US/Eastern</td><td>Pipeline dark: 120 frame superdark with hotpixels from 01/12/2003</td></tr>
        <tr><td><a href="http://archive.stsci.edu/cgi-bin/dataset_lookup?dataset_input_list=ncc17444u*">ncc17444u.r3h</a></td><td>FULL</td><td>ON</td><td>7</td><td>Dec 01 2003  12:02AM</td><td>INFLIGHT</td><td>11302</td><td>Dec 15 2003  08:44PM</td><td>2003/12/16 15:38:00 US/Eastern</td><td>Pipeline dark: 120 frame superdark with hotpixels from 01/12/2003</td></tr>
        <tr><td><a href="http://archive.stsci.edu/cgi-bin/dataset_lookup?dataset_input_list=ncc17441u*">ncc17441u.r3h</a></td><td>FULL</td><td>OFF</td><td>15</td><td>Dec 01 2003  12:02AM</td><td>INFLIGHT</td><td>11302</td><td>Dec 15 2003  08:44PM</td><td>2003/12/16 15:38:00 US/Eastern</td><td>Pipeline dark: 120 frame superdark with hotpixels from 01/12/2003</td></tr>
        <tr><td><a href="http://archive.stsci.edu/cgi-bin/dataset_lookup?dataset_input_list=ncc17442u*">ncc17442u.r3h</a></td><td>FULL</td><td>ON</td><td>15</td><td>Dec 01 2003  12:02AM</td><td>INFLIGHT</td><td>11302</td><td>Dec 15 2003  08:44PM</td><td>2003/12/16 15:38:00 US/Eastern</td><td>Pipeline dark: 120 frame superdark with hotpixels from 01/12/2003</td></tr>
        <tr><td><a href="http://archive.stsci.edu/cgi-bin/dataset_lookup?dataset_input_list=nc308279u*">nc308279u.r3h</a></td><td>FULL</td><td>OFF</td><td>7</td><td>Nov 24 2003  02:20AM</td><td>INFLIGHT</td><td>11297</td><td>Dec 08 2003  06:04PM</td><td>2003/12/09</td><td>Pipeline dark: 120 frame superdark with hotpixels from 24/11/2003</td></tr>
        <tr><td><a href="http://archive.stsci.edu/cgi-bin/dataset_lookup?dataset_input_list=nc30827au*">nc30827au.r3h</a></td><td>FULL</td><td>ON</td><td>7</td><td>Nov 24 2003  02:20AM</td><td>INFLIGHT</td><td>11297</td><td>Dec 08 2003  06:04PM</td><td>2003/12/09</td><td>Pipeline dark: 120 frame superdark with hotpixels from 24/11/2003</td></tr>
        <tr><td><a href="http://archive.stsci.edu/cgi-bin/dataset_lookup?dataset_input_list=nc308272u*">nc308272u.r3h</a></td><td>FULL</td><td>OFF</td><td>15</td><td>Nov 24 2003  02:20AM</td><td>INFLIGHT</td><td>11297</td><td>Dec 08 2003  06:04PM</td><td>2003/12/09</td><td>Pipeline dark: 120 frame superdark with hotpixels from 24/11/2003</td></tr>
        <tr><td><a href="http://archive.stsci.edu/cgi-bin/dataset_lookup?dataset_input_list=nc308278u*">nc308278u.r3h</a></td><td>FULL</td><td>ON</td><td>15</td><td>Nov 24 2003  02:20AM</td><td>INFLIGHT</td><td>11297</td><td>Dec 08 2003  06:04PM</td><td>2003/12/09</td><td>Pipeline dark: 120 frame superdark with hotpixels from 24/11/2003</td></tr>
        <tr><td><a href="http://archive.stsci.edu/cgi-bin/dataset_lookup?dataset_input_list=nc308175u*">nc308175u.r3h</a></td><td>FULL</td><td>OFF</td><td>7</td><td>Nov 17 2003  02:56AM</td><td>INFLIGHT</td><td>11297</td><td>Dec 08 2003  06:04PM</td><td>2003/12/09</td><td>Pipeline dark: 120 frame superdark with hotpixels from 17/11/2003</td></tr>
        <tr><td><a href="http://archive.stsci.edu/cgi-bin/dataset_lookup?dataset_input_list=nc308176u*">nc308176u.r3h</a></td><td>FULL</td><td>ON</td><td>7</td><td>Nov 17 2003  02:56AM</td><td>INFLIGHT</td><td>11297</td><td>Dec 08 2003  06:04PM</td><td>2003/12/09</td><td>Pipeline dark: 120 frame superdark with hotpixels from 17/11/2003</td></tr>
        <tr><td><a href="http://archive.stsci.edu/cgi-bin/dataset_lookup?dataset_input_list=nc308173u*">nc308173u.r3h</a></td><td>FULL</td><td>OFF</td><td>15</td><td>Nov 17 2003  02:56AM</td><td>INFLIGHT</td><td>11297</td><td>Dec 08 2003  06:04PM</td><td>2003/12/09</td><td>Pipeline dark: 120 frame superdark with hotpixels from 17/11/2003</td></tr>
        <tr><td><a href="http://archive.stsci.edu/cgi-bin/dataset_lookup?dataset_input_list=nc308174u*">nc308174u.r3h</a></td><td>FULL</td><td>ON</td><td>15</td><td>Nov 17 2003  02:56AM</td><td>INFLIGHT</td><td>11297</td><td>Dec 08 2003  06:04PM</td><td>2003/12/09</td><td>Pipeline dark: 120 frame superdark with hotpixels from 17/11/2003</td></tr>
        <tr><td><a href="http://archive.stsci.edu/cgi-bin/dataset_lookup?dataset_input_list=nc30808qu*">nc30808qu.r3h</a></td><td>FULL</td><td>OFF</td><td>7</td><td>Nov 14 2003  06:11AM</td><td>INFLIGHT</td><td>11297</td><td>Dec 08 2003  06:04PM</td><td>2003/12/09</td><td>Pipeline dark: 120 frame superdark with hotpixels from 14/11/2003</td></tr>
        <tr><td><a href="http://archive.stsci.edu/cgi-bin/dataset_lookup?dataset_input_list=nc30808ru*">nc30808ru.r3h</a></td><td>FULL</td><td>ON</td><td>7</td><td>Nov 14 2003  06:11AM</td><td>INFLIGHT</td><td>11297</td><td>Dec 08 2003  06:04PM</td><td>2003/12/09</td><td>Pipeline dark: 120 frame superdark with hotpixels from 14/11/2003</td></tr>
        <tr><td><a href="http://archive.stsci.edu/cgi-bin/dataset_lookup?dataset_input_list=nc30808ju*">nc30808ju.r3h</a></td><td>FULL</td><td>OFF</td><td>15</td><td>Nov 14 2003  06:11AM</td><td>INFLIGHT</td><td>11297</td><td>Dec 08 2003  06:04PM</td><td>2003/12/09</td><td>Pipeline dark: 120 frame superdark with hotpixels from 14/11/2003</td></tr>
        <tr><td><a href="http://archive.stsci.edu/cgi-bin/dataset_lookup?dataset_input_list=nc30808pu*">nc30808pu.r3h</a></td><td>FULL</td><td>ON</td><td>15</td><td>Nov 14 2003  06:11AM</td><td>INFLIGHT</td><td>11297</td><td>Dec 08 2003  06:04PM</td><td>2003/12/09</td><td>Pipeline dark: 120 frame superdark with hotpixels from 14/11/2003</td></tr>
        <tr><td><a href="http://archive.stsci.edu/cgi-bin/dataset_lookup?dataset_input_list=nbj08268u*">nbj08268u.r3h</a></td><td>FULL</td><td>OFF</td><td>7</td><td>Nov 10 2003  10:25AM</td><td>INFLIGHT</td><td>11294</td><td>Nov 19 2003  02:03PM</td><td>2003/11/21</td><td>Pipeline dark: 120 frame superdark with hotpixels from 10/11/2003</td></tr>
        <tr><td><a href="http://archive.stsci.edu/cgi-bin/dataset_lookup?dataset_input_list=nbj08269u*">nbj08269u.r3h</a></td><td>FULL</td><td>ON</td><td>7</td><td>Nov 10 2003  10:25AM</td><td>INFLIGHT</td><td>11294</td><td>Nov 19 2003  02:03PM</td><td>2003/11/21</td><td>Pipeline dark: 120 frame superdark with hotpixels from 10/11/2003</td></tr>
        <tr><td><a href="http://archive.stsci.edu/cgi-bin/dataset_lookup?dataset_input_list=nbj08266u*">nbj08266u.r3h</a></td><td>FULL</td><td>OFF</td><td>15</td><td>Nov 10 2003  10:25AM</td><td>INFLIGHT</td><td>11294</td><td>Nov 19 2003  02:03PM</td><td>2003/11/21</td><td>Pipeline dark: 120 frame superdark with hotpixels from 10/11/2003</td></tr>
        <tr><td><a href="http://archive.stsci.edu/cgi-bin/dataset_lookup?dataset_input_list=nbj08267u*">nbj08267u.r3h</a></td><td>FULL</td><td>ON</td><td>15</td><td>Nov 10 2003  10:25AM</td><td>INFLIGHT</td><td>11294</td><td>Nov 19 2003  02:03PM</td><td>2003/11/21</td><td>Pipeline dark: 120 frame superdark with hotpixels from 10/11/2003</td></tr>
        <tr><td><a href="http://archive.stsci.edu/cgi-bin/dataset_lookup?dataset_input_list=nbj0816pu*">nbj0816pu.r3h</a></td><td>FULL</td><td>OFF</td><td>7</td><td>Nov 03 2003  03:08AM</td><td>INFLIGHT</td><td>11294</td><td>Nov 19 2003  02:03PM</td><td>2003/11/21</td><td>Pipeline dark: 120 frame superdark with hotpixels from 03/11/2003</td></tr>
        <tr><td><a href="http://archive.stsci.edu/cgi-bin/dataset_lookup?dataset_input_list=nbj0816qu*">nbj0816qu.r3h</a></td><td>FULL</td><td>ON</td><td>7</td><td>Nov 03 2003  03:08AM</td><td>INFLIGHT</td><td>11294</td><td>Nov 19 2003  02:03PM</td><td>2003/11/21</td><td>Pipeline dark: 120 frame superdark with hotpixels from 03/11/2003</td></tr>
        <tr><td><a href="http://archive.stsci.edu/cgi-bin/dataset_lookup?dataset_input_list=nbj0816mu*">nbj0816mu.r3h</a></td><td>FULL</td><td>OFF</td><td>15</td><td>Nov 03 2003  03:08AM</td><td>INFLIGHT</td><td>11294</td><td>Nov 19 2003  02:03PM</td><td>2003/11/21</td><td>Pipeline dark: 120 frame superdark with hotpixels from 03/11/2003</td></tr>
        <tr><td><a href="http://archive.stsci.edu/cgi-bin/dataset_lookup?dataset_input_list=nbj0816ou*">nbj0816ou.r3h</a></td><td>FULL</td><td>ON</td><td>15</td><td>Nov 03 2003  03:08AM</td><td>INFLIGHT</td><td>11294</td><td>Nov 19 2003  02:03PM</td><td>2003/11/21</td><td>Pipeline dark: 120 frame superdark with hotpixels from 03/11/2003</td></tr>
        <tr><td><a href="http://archive.stsci.edu/cgi-bin/dataset_lookup?dataset_input_list=nav0845au*">nav0845au.r3h</a></td><td>FULL</td><td>OFF</td><td>7</td><td>Oct 27 2003  03:01AM</td><td>INFLIGHT</td><td>11279</td><td>Nov 03 2003  04:13PM</td><td>2003/11/03</td><td>Pipeline dark: 120 frame superdark with hotpixels from 27/10/2003</td></tr>
        <tr><td><a href="http://archive.stsci.edu/cgi-bin/dataset_lookup?dataset_input_list=nav0845bu*">nav0845bu.r3h</a></td><td>FULL</td><td>ON</td><td>7</td><td>Oct 27 2003  03:01AM</td><td>INFLIGHT</td><td>11279</td><td>Nov 03 2003  04:13PM</td><td>2003/11/03</td><td>Pipeline dark: 120 frame superdark with hotpixels from 27/10/2003</td></tr>
        <tr><td><a href="http://archive.stsci.edu/cgi-bin/dataset_lookup?dataset_input_list=nav08458u*">nav08458u.r3h</a></td><td>FULL</td><td>OFF</td><td>15</td><td>Oct 27 2003  03:01AM</td><td>INFLIGHT</td><td>11279</td><td>Nov 03 2003  04:13PM</td><td>2003/11/03</td><td>Pipeline dark: 120 frame superdark with hotpixels from 27/10/2003</td></tr>
        <tr><td><a href="http://archive.stsci.edu/cgi-bin/dataset_lookup?dataset_input_list=nav08459u*">nav08459u.r3h</a></td><td>FULL</td><td>ON</td><td>15</td><td>Oct 27 2003  03:01AM</td><td>INFLIGHT</td><td>11279</td><td>Nov 03 2003  04:13PM</td><td>2003/11/03</td><td>Pipeline dark: 120 frame superdark with hotpixels from 27/10/2003</td></tr>
        <tr><td><a href="http://archive.stsci.edu/cgi-bin/dataset_lookup?dataset_input_list=nav0838bu*">nav0838bu.r3h</a></td><td>FULL</td><td>OFF</td><td>7</td><td>Oct 20 2003  05:12AM</td><td>INFLIGHT</td><td>11279</td><td>Nov 03 2003  04:13PM</td><td>2003/11/03</td><td>Pipeline dark: 120 frame superdark with hotpixels from 20/10/2003</td></tr>
        <tr><td><a href="http://archive.stsci.edu/cgi-bin/dataset_lookup?dataset_input_list=nav0838cu*">nav0838cu.r3h</a></td><td>FULL</td><td>ON</td><td>7</td><td>Oct 20 2003  05:12AM</td><td>INFLIGHT</td><td>11279</td><td>Nov 03 2003  04:13PM</td><td>2003/11/03</td><td>Pipeline dark: 120 frame superdark with hotpixels from 20/10/2003</td></tr>
        <tr><td><a href="http://archive.stsci.edu/cgi-bin/dataset_lookup?dataset_input_list=nav08389u*">nav08389u.r3h</a></td><td>FULL</td><td>OFF</td><td>15</td><td>Oct 20 2003  05:12AM</td><td>INFLIGHT</td><td>11279</td><td>Nov 03 2003  04:13PM</td><td>2003/11/03</td><td>Pipeline dark: 120 frame superdark with hotpixels from 20/10/2003</td></tr>
        <tr><td><a href="http://archive.stsci.edu/cgi-bin/dataset_lookup?dataset_input_list=nav0838au*">nav0838au.r3h</a></td><td>FULL</td><td>ON</td><td>15</td><td>Oct 20 2003  05:12AM</td><td>INFLIGHT</td><td>11279</td><td>Nov 03 2003  04:13PM</td><td>2003/11/03</td><td>Pipeline dark: 120 frame superdark with hotpixels from 20/10/2003</td></tr>
        <tr><td><a href="http://archive.stsci.edu/cgi-bin/dataset_lookup?dataset_input_list=nal0919pu*">nal0919pu.r3h</a></td><td>FULL</td><td>OFF</td><td>7</td><td>Oct 13 2003  04:45AM</td><td>INFLIGHT</td><td>11269</td><td>Oct 21 2003  04:26PM</td><td>2003/10/21</td><td>Pipeline dark: 120 frame superdark with hotpixels from 13/10/2003</td></tr>
        <tr><td><a href="http://archive.stsci.edu/cgi-bin/dataset_lookup?dataset_input_list=nal0919qu*">nal0919qu.r3h</a></td><td>FULL</td><td>ON</td><td>7</td><td>Oct 13 2003  04:45AM</td><td>INFLIGHT</td><td>11269</td><td>Oct 21 2003  04:26PM</td><td>2003/10/21</td><td>Pipeline dark: 120 frame superdark with hotpixels from 13/10/2003</td></tr>
        <tr><td><a href="http://archive.stsci.edu/cgi-bin/dataset_lookup?dataset_input_list=nal0919nu*">nal0919nu.r3h</a></td><td>FULL</td><td>OFF</td><td>15</td><td>Oct 13 2003  04:45AM</td><td>INFLIGHT</td><td>11269</td><td>Oct 21 2003  04:26PM</td><td>2003/10/21</td><td>Pipeline dark: 120 frame superdark with hotpixels from 13/10/2003</td></tr>
        <tr><td><a href="http://archive.stsci.edu/cgi-bin/dataset_lookup?dataset_input_list=nal0919ou*">nal0919ou.r3h</a></td><td>FULL</td><td>ON</td><td>15</td><td>Oct 13 2003  04:45AM</td><td>INFLIGHT</td><td>11269</td><td>Oct 21 2003  04:26PM</td><td>2003/10/21</td><td>Pipeline dark: 120 frame superdark with hotpixels from 13/10/2003</td></tr>
        <tr><td><a href="http://archive.stsci.edu/cgi-bin/dataset_lookup?dataset_input_list=na81405ou*">na81405ou.r3h</a></td><td>FULL</td><td>OFF</td><td>7</td><td>Oct 06 2003  02:31AM</td><td>INFLIGHT</td><td>11266</td><td>Oct 09 2003  03:47PM</td><td>2003/10/09</td><td>Pipeline dark: 120 frame superdark with hotpixels from 06/10/2003</td></tr>
        <tr><td><a href="http://archive.stsci.edu/cgi-bin/dataset_lookup?dataset_input_list=na81405pu*">na81405pu.r3h</a></td><td>FULL</td><td>ON</td><td>7</td><td>Oct 06 2003  02:31AM</td><td>INFLIGHT</td><td>11266</td><td>Oct 09 2003  03:47PM</td><td>2003/10/09</td><td>Pipeline dark: 120 frame superdark with hotpixels from 06/10/2003</td></tr>
        <tr><td><a href="http://archive.stsci.edu/cgi-bin/dataset_lookup?dataset_input_list=na81405mu*">na81405mu.r3h</a></td><td>FULL</td><td>OFF</td><td>15</td><td>Oct 06 2003  02:31AM</td><td>INFLIGHT</td><td>11266</td><td>Oct 09 2003  03:47PM</td><td>2003/10/09</td><td>Pipeline dark: 120 frame superdark with hotpixels from 06/10/2003</td></tr>
        <tr><td><a href="http://archive.stsci.edu/cgi-bin/dataset_lookup?dataset_input_list=na81405nu*">na81405nu.r3h</a></td><td>FULL</td><td>ON</td><td>15</td><td>Oct 06 2003  02:31AM</td><td>INFLIGHT</td><td>11266</td><td>Oct 09 2003  03:47PM</td><td>2003/10/09</td><td>Pipeline dark: 120 frame superdark with hotpixels from 06/10/2003</td></tr>
        <tr><td><a href="http://archive.stsci.edu/cgi-bin/dataset_lookup?dataset_input_list=na813570u*">na813570u.r3h</a></td><td>FULL</td><td>OFF</td><td>7</td><td>Sep 29 2003  01:28AM</td><td>INFLIGHT</td><td>11266</td><td>Oct 09 2003  03:47PM</td><td>2003/10/09</td><td>Pipeline dark: 120 frame superdark with hotpixels from 29/09/2003</td></tr>
        <tr><td><a href="http://archive.stsci.edu/cgi-bin/dataset_lookup?dataset_input_list=na813571u*">na813571u.r3h</a></td><td>FULL</td><td>ON</td><td>7</td><td>Sep 29 2003  01:28AM</td><td>INFLIGHT</td><td>11266</td><td>Oct 09 2003  03:47PM</td><td>2003/10/09</td><td>Pipeline dark: 120 frame superdark with hotpixels from 29/09/2003</td></tr>
        <tr><td><a href="http://archive.stsci.edu/cgi-bin/dataset_lookup?dataset_input_list=na81356su*">na81356su.r3h</a></td><td>FULL</td><td>OFF</td><td>15</td><td>Sep 29 2003  01:28AM</td><td>INFLIGHT</td><td>11266</td><td>Oct 09 2003  03:47PM</td><td>2003/10/09</td><td>Pipeline dark: 120 frame superdark with hotpixels from 29/09/2003</td></tr>
        <tr><td><a href="http://archive.stsci.edu/cgi-bin/dataset_lookup?dataset_input_list=na81356tu*">na81356tu.r3h</a></td><td>FULL</td><td>ON</td><td>15</td><td>Sep 29 2003  01:28AM</td><td>INFLIGHT</td><td>11266</td><td>Oct 09 2003  03:47PM</td><td>2003/10/09</td><td>Pipeline dark: 120 frame superdark with hotpixels from 29/09/2003</td></tr>
        <tr><td><a href="http://archive.stsci.edu/cgi-bin/dataset_lookup?dataset_input_list=n9r12340u*">n9r12340u.r3h</a></td><td>FULL</td><td>OFF</td><td>7</td><td>Sep 23 2003  07:29AM</td><td>INFLIGHT</td><td>11260</td><td>Sep 29 2003  02:14PM</td><td>2003/09/29 00:02:00 GMT-4</td><td>Pipeline dark: 120 frame superdark with hotpixels from 23/09/2003</td></tr>
        <tr><td><a href="http://archive.stsci.edu/cgi-bin/dataset_lookup?dataset_input_list=n9r12341u*">n9r12341u.r3h</a></td><td>FULL</td><td>ON</td><td>7</td><td>Sep 23 2003  07:29AM</td><td>INFLIGHT</td><td>11260</td><td>Sep 29 2003  02:14PM</td><td>2003/09/29 00:02:00 GMT-4</td><td>Pipeline dark: 120 frame superdark with hotpixels from 23/09/2003</td></tr>
        <tr><td><a href="http://archive.stsci.edu/cgi-bin/dataset_lookup?dataset_input_list=n9r1233su*">n9r1233su.r3h</a></td><td>FULL</td><td>OFF</td><td>15</td><td>Sep 23 2003  07:29AM</td><td>INFLIGHT</td><td>11260</td><td>Sep 29 2003  02:14PM</td><td>2003/09/29 00:02:00 GMT-4</td><td>Pipeline dark: 120 frame superdark with hotpixels from 23/09/2003</td></tr>
        <tr><td><a href="http://archive.stsci.edu/cgi-bin/dataset_lookup?dataset_input_list=n9r1233tu*">n9r1233tu.r3h</a></td><td>FULL</td><td>ON</td><td>15</td><td>Sep 23 2003  07:29AM</td><td>INFLIGHT</td><td>11260</td><td>Sep 29 2003  02:14PM</td><td>2003/09/29 00:02:00 GMT-4</td><td>Pipeline dark: 120 frame superdark with hotpixels from 23/09/2003</td></tr>
        <tr><td><a href="http://archive.stsci.edu/cgi-bin/dataset_lookup?dataset_input_list=n9r1221nu*">n9r1221nu.r3h</a></td><td>FULL</td><td>OFF</td><td>7</td><td>Sep 22 2003  09:54AM</td><td>INFLIGHT</td><td>11260</td><td>Sep 29 2003  02:14PM</td><td>2003/09/29 00:02:00 GMT-4</td><td>Pipeline dark: 120 frame superdark with hotpixels from 22/09/2003</td></tr>
        <tr><td><a href="http://archive.stsci.edu/cgi-bin/dataset_lookup?dataset_input_list=n9r1221ou*">n9r1221ou.r3h</a></td><td>FULL</td><td>ON</td><td>7</td><td>Sep 22 2003  09:54AM</td><td>INFLIGHT</td><td>11260</td><td>Sep 29 2003  02:14PM</td><td>2003/09/29 00:02:00 GMT-4</td><td>Pipeline dark: 120 frame superdark with hotpixels from 22/09/2003</td></tr>
        <tr><td><a href="http://archive.stsci.edu/cgi-bin/dataset_lookup?dataset_input_list=n9r1221lu*">n9r1221lu.r3h</a></td><td>FULL</td><td>OFF</td><td>15</td><td>Sep 22 2003  09:54AM</td><td>INFLIGHT</td><td>11260</td><td>Sep 29 2003  02:14PM</td><td>2003/09/29 00:02:00 GMT-4</td><td>Pipeline dark: 120 frame superdark with hotpixels from 22/09/2003</td></tr>
        <tr><td><a href="http://archive.stsci.edu/cgi-bin/dataset_lookup?dataset_input_list=n9r1221mu*">n9r1221mu.r3h</a></td><td>FULL</td><td>ON</td><td>15</td><td>Sep 22 2003  09:54AM</td><td>INFLIGHT</td><td>11260</td><td>Sep 29 2003  02:14PM</td><td>2003/09/29 00:02:00 GMT-4</td><td>Pipeline dark: 120 frame superdark with hotpixels from 22/09/2003</td></tr>
        <tr><td><a href="http://archive.stsci.edu/cgi-bin/dataset_lookup?dataset_input_list=n9r1211hu*">n9r1211hu.r3h</a></td><td>FULL</td><td>OFF</td><td>7</td><td>Sep 15 2003  04:17AM</td><td>INFLIGHT</td><td>11260</td><td>Sep 29 2003  02:14PM</td><td>2003/09/29 00:02:00 GMT-4</td><td>Pipeline dark: 120 frame superdark with hotpixels from 15/09/2003</td></tr>
        <tr><td><a href="http://archive.stsci.edu/cgi-bin/dataset_lookup?dataset_input_list=n9r1211iu*">n9r1211iu.r3h</a></td><td>FULL</td><td>ON</td><td>7</td><td>Sep 15 2003  04:17AM</td><td>INFLIGHT</td><td>11260</td><td>Sep 29 2003  02:14PM</td><td>2003/09/29 00:02:00 GMT-4</td><td>Pipeline dark: 120 frame superdark with hotpixels from 15/09/2003</td></tr>
        <tr><td><a href="http://archive.stsci.edu/cgi-bin/dataset_lookup?dataset_input_list=n9r1211fu*">n9r1211fu.r3h</a></td><td>FULL</td><td>OFF</td><td>15</td><td>Sep 15 2003  04:17AM</td><td>INFLIGHT</td><td>11260</td><td>Sep 29 2003  02:14PM</td><td>2003/09/29 00:02:00 GMT-4</td><td>Pipeline dark: 120 frame superdark with hotpixels from 15/09/2003</td></tr>
        <tr><td><a href="http://archive.stsci.edu/cgi-bin/dataset_lookup?dataset_input_list=n9r1211gu*">n9r1211gu.r3h</a></td><td>FULL</td><td>ON</td><td>15</td><td>Sep 15 2003  04:17AM</td><td>INFLIGHT</td><td>11260</td><td>Sep 29 2003  02:14PM</td><td>2003/09/29 00:02:00 GMT-4</td><td>Pipeline dark: 120 frame superdark with hotpixels from 15/09/2003</td></tr>
        <tr><td><a href="http://archive.stsci.edu/cgi-bin/dataset_lookup?dataset_input_list=n9i1213du*">n9i1213du.r3h</a></td><td>FULL</td><td>OFF</td><td>7</td><td>Sep 08 2003  02:47AM</td><td>INFLIGHT</td><td>11256</td><td>Sep 24 2003  08:58PM</td><td>2003/09/24</td><td>Pipeline dark: 120 frame superdark with hotpixels from 08/09/2003</td></tr>
        <tr><td><a href="http://archive.stsci.edu/cgi-bin/dataset_lookup?dataset_input_list=n9i1213eu*">n9i1213eu.r3h</a></td><td>FULL</td><td>ON</td><td>7</td><td>Sep 08 2003  02:47AM</td><td>INFLIGHT</td><td>11256</td><td>Sep 24 2003  08:58PM</td><td>2003/09/24</td><td>Pipeline dark: 120 frame superdark with hotpixels from 08/09/2003</td></tr>
        <tr><td><a href="http://archive.stsci.edu/cgi-bin/dataset_lookup?dataset_input_list=n9i1213bu*">n9i1213bu.r3h</a></td><td>FULL</td><td>OFF</td><td>15</td><td>Sep 08 2003  02:47AM</td><td>INFLIGHT</td><td>11256</td><td>Sep 24 2003  08:58PM</td><td>2003/09/24</td><td>Pipeline dark: 120 frame superdark with hotpixels from 08/09/2003</td></tr>
        <tr><td><a href="http://archive.stsci.edu/cgi-bin/dataset_lookup?dataset_input_list=n9i1213cu*">n9i1213cu.r3h</a></td><td>FULL</td><td>ON</td><td>15</td><td>Sep 08 2003  02:47AM</td><td>INFLIGHT</td><td>11256</td><td>Sep 24 2003  08:58PM</td><td>2003/09/24</td><td>Pipeline dark: 120 frame superdark with hotpixels from 08/09/2003</td></tr>
        <tr><td><a href="http://archive.stsci.edu/cgi-bin/dataset_lookup?dataset_input_list=n9a0904bu*">n9a0904bu.r3h</a></td><td>FULL</td><td>OFF</td><td>7</td><td>Sep 01 2003  12:55AM</td><td>INFLIGHT</td><td>11244</td><td>Sep 15 2003  02:02PM</td><td>2003/09/15</td><td>Pipeline dark: 120 frame superdark with hotpixels from 01/09/2003</td></tr>
        <tr><td><a href="http://archive.stsci.edu/cgi-bin/dataset_lookup?dataset_input_list=n9a0904cu*">n9a0904cu.r3h</a></td><td>FULL</td><td>ON</td><td>7</td><td>Sep 01 2003  12:55AM</td><td>INFLIGHT</td><td>11244</td><td>Sep 15 2003  02:02PM</td><td>2003/09/15</td><td>Pipeline dark: 120 frame superdark with hotpixels from 01/09/2003</td></tr>
        <tr><td><a href="http://archive.stsci.edu/cgi-bin/dataset_lookup?dataset_input_list=n9a09049u*">n9a09049u.r3h</a></td><td>FULL</td><td>OFF</td><td>15</td><td>Sep 01 2003  12:55AM</td><td>INFLIGHT</td><td>11244</td><td>Sep 15 2003  02:02PM</td><td>2003/09/15</td><td>Pipeline dark: 120 frame superdark with hotpixels from 01/09/2003</td></tr>
        <tr><td><a href="http://archive.stsci.edu/cgi-bin/dataset_lookup?dataset_input_list=n9a0904au*">n9a0904au.r3h</a></td><td>FULL</td><td>ON</td><td>15</td><td>Sep 01 2003  12:55AM</td><td>INFLIGHT</td><td>11244</td><td>Sep 15 2003  02:02PM</td><td>2003/09/15</td><td>Pipeline dark: 120 frame superdark with hotpixels from 01/09/2003</td></tr>
        <tr><td><a href="http://archive.stsci.edu/cgi-bin/dataset_lookup?dataset_input_list=n8r0837ju*">n8r0837ju.r3h</a></td><td>FULL</td><td>OFF</td><td>7</td><td>Aug 25 2003  01:17AM</td><td>INFLIGHT</td><td>11237</td><td>Aug 27 2003  02:32PM</td><td>2003/08/28</td><td>Pipeline dark: 120 frame superdark with hotpixels from 25/08/2003</td></tr>
        <tr><td><a href="http://archive.stsci.edu/cgi-bin/dataset_lookup?dataset_input_list=n8r0837ku*">n8r0837ku.r3h</a></td><td>FULL</td><td>ON</td><td>7</td><td>Aug 25 2003  01:17AM</td><td>INFLIGHT</td><td>11237</td><td>Aug 27 2003  02:32PM</td><td>2003/08/28</td><td>Pipeline dark: 120 frame superdark with hotpixels from 25/08/2003</td></tr>
        <tr><td><a href="http://archive.stsci.edu/cgi-bin/dataset_lookup?dataset_input_list=n8r0837hu*">n8r0837hu.r3h</a></td><td>FULL</td><td>OFF</td><td>15</td><td>Aug 25 2003  01:17AM</td><td>INFLIGHT</td><td>11237</td><td>Aug 27 2003  02:32PM</td><td>2003/08/28</td><td>Pipeline dark: 120 frame superdark with hotpixels from 25/08/2003</td></tr>
        <tr><td><a href="http://archive.stsci.edu/cgi-bin/dataset_lookup?dataset_input_list=n8r0837iu*">n8r0837iu.r3h</a></td><td>FULL</td><td>ON</td><td>15</td><td>Aug 25 2003  01:17AM</td><td>INFLIGHT</td><td>11237</td><td>Aug 27 2003  02:32PM</td><td>2003/08/28</td><td>Pipeline dark: 120 frame superdark with hotpixels from 25/08/2003</td></tr>
        <tr><td><a href="http://archive.stsci.edu/cgi-bin/dataset_lookup?dataset_input_list=n8r08228u*">n8r08228u.r3h</a></td><td>FULL</td><td>OFF</td><td>7</td><td>Aug 18 2003  01:53AM</td><td>INFLIGHT</td><td>11237</td><td>Aug 27 2003  02:32PM</td><td>2003/08/28</td><td>Pipeline dark: 120 frame superdark with hotpixels from 18/08/2003</td></tr>
        <tr><td><a href="http://archive.stsci.edu/cgi-bin/dataset_lookup?dataset_input_list=n8r08229u*">n8r08229u.r3h</a></td><td>FULL</td><td>ON</td><td>7</td><td>Aug 18 2003  01:53AM</td><td>INFLIGHT</td><td>11237</td><td>Aug 27 2003  02:32PM</td><td>2003/08/28</td><td>Pipeline dark: 120 frame superdark with hotpixels from 18/08/2003</td></tr>
        <tr><td><a href="http://archive.stsci.edu/cgi-bin/dataset_lookup?dataset_input_list=n8r08226u*">n8r08226u.r3h</a></td><td>FULL</td><td>OFF</td><td>15</td><td>Aug 18 2003  01:53AM</td><td>INFLIGHT</td><td>11237</td><td>Aug 27 2003  02:32PM</td><td>2003/08/28</td><td>Pipeline dark: 120 frame superdark with hotpixels from 18/08/2003</td></tr>
        <tr><td><a href="http://archive.stsci.edu/cgi-bin/dataset_lookup?dataset_input_list=n8r08227u*">n8r08227u.r3h</a></td><td>FULL</td><td>ON</td><td>15</td><td>Aug 18 2003  01:53AM</td><td>INFLIGHT</td><td>11237</td><td>Aug 27 2003  02:32PM</td><td>2003/08/28</td><td>Pipeline dark: 120 frame superdark with hotpixels from 18/08/2003</td></tr>
        <tr><td><a href="http://archive.stsci.edu/cgi-bin/dataset_lookup?dataset_input_list=n8g1205nu*">n8g1205nu.r3h</a></td><td>FULL</td><td>OFF</td><td>7</td><td>Aug 11 2003  03:36AM</td><td>INFLIGHT</td><td>11233</td><td>Aug 19 2003  03:48PM</td><td>2003/08/20</td><td>Pipeline dark: 120 frame superdark with hotpixels from 11/08/2003</td></tr>
        <tr><td><a href="http://archive.stsci.edu/cgi-bin/dataset_lookup?dataset_input_list=n8g1205ou*">n8g1205ou.r3h</a></td><td>FULL</td><td>ON</td><td>7</td><td>Aug 11 2003  03:36AM</td><td>INFLIGHT</td><td>11233</td><td>Aug 19 2003  03:48PM</td><td>2003/08/20</td><td>Pipeline dark: 120 frame superdark with hotpixels from 11/08/2003</td></tr>
        <tr><td><a href="http://archive.stsci.edu/cgi-bin/dataset_lookup?dataset_input_list=n8g1205lu*">n8g1205lu.r3h</a></td><td>FULL</td><td>OFF</td><td>15</td><td>Aug 11 2003  03:36AM</td><td>INFLIGHT</td><td>11233</td><td>Aug 19 2003  03:48PM</td><td>2003/08/20</td><td>Pipeline dark: 120 frame superdark with hotpixels from 11/08/2003</td></tr>
        <tr><td><a href="http://archive.stsci.edu/cgi-bin/dataset_lookup?dataset_input_list=n8g1205mu*">n8g1205mu.r3h</a></td><td>FULL</td><td>ON</td><td>15</td><td>Aug 11 2003  03:36AM</td><td>INFLIGHT</td><td>11233</td><td>Aug 19 2003  03:48PM</td><td>2003/08/20</td><td>Pipeline dark: 120 frame superdark with hotpixels from 11/08/2003</td></tr>
        <tr><td><a href="http://archive.stsci.edu/cgi-bin/dataset_lookup?dataset_input_list=n8g1153eu*">n8g1153eu.r3h</a></td><td>FULL</td><td>OFF</td><td>7</td><td>Aug 06 2003  10:16AM</td><td>INFLIGHT</td><td>11233</td><td>Aug 19 2003  03:48PM</td><td>2003/08/20</td><td>Pipeline dark: 120 frame superdark with hotpixels from 06/08/2003</td></tr>
        <tr><td><a href="http://archive.stsci.edu/cgi-bin/dataset_lookup?dataset_input_list=n8g1153fu*">n8g1153fu.r3h</a></td><td>FULL</td><td>ON</td><td>7</td><td>Aug 06 2003  10:16AM</td><td>INFLIGHT</td><td>11233</td><td>Aug 19 2003  03:48PM</td><td>2003/08/20</td><td>Pipeline dark: 120 frame superdark with hotpixels from 06/08/2003</td></tr>
        <tr><td><a href="http://archive.stsci.edu/cgi-bin/dataset_lookup?dataset_input_list=n8g1153cu*">n8g1153cu.r3h</a></td><td>FULL</td><td>OFF</td><td>15</td><td>Aug 06 2003  10:16AM</td><td>INFLIGHT</td><td>11233</td><td>Aug 19 2003  03:48PM</td><td>2003/08/20</td><td>Pipeline dark: 120 frame superdark with hotpixels from 06/08/2003</td></tr>
        <tr><td><a href="http://archive.stsci.edu/cgi-bin/dataset_lookup?dataset_input_list=n8g1153du*">n8g1153du.r3h</a></td><td>FULL</td><td>ON</td><td>15</td><td>Aug 06 2003  10:16AM</td><td>INFLIGHT</td><td>11233</td><td>Aug 19 2003  03:48PM</td><td>2003/08/20</td><td>Pipeline dark: 120 frame superdark with hotpixels from 06/08/2003</td></tr>
        <tr><td><a href="http://archive.stsci.edu/cgi-bin/dataset_lookup?dataset_input_list=n8c0837tu*">n8c0837tu.r3h</a></td><td>FULL</td><td>OFF</td><td>7</td><td>Aug 04 2003  08:33AM</td><td>INFLIGHT</td><td>11228</td><td>Aug 12 2003  03:01PM</td><td>2003/08/12</td><td>Pipeline dark: 120 frame superdark with hotpixels from 04/08/2003</td></tr>
        <tr><td><a href="http://archive.stsci.edu/cgi-bin/dataset_lookup?dataset_input_list=n8c08380u*">n8c08380u.r3h</a></td><td>FULL</td><td>ON</td><td>7</td><td>Aug 04 2003  08:33AM</td><td>INFLIGHT</td><td>11228</td><td>Aug 12 2003  03:01PM</td><td>2003/08/12</td><td>Pipeline dark: 120 frame superdark with hotpixels from 04/08/2003</td></tr>
        <tr><td><a href="http://archive.stsci.edu/cgi-bin/dataset_lookup?dataset_input_list=n8c0837ru*">n8c0837ru.r3h</a></td><td>FULL</td><td>OFF</td><td>15</td><td>Aug 04 2003  08:33AM</td><td>INFLIGHT</td><td>11228</td><td>Aug 12 2003  03:01PM</td><td>2003/08/12</td><td>Pipeline dark: 120 frame superdark with hotpixels from 04/08/2003</td></tr>
        <tr><td><a href="http://archive.stsci.edu/cgi-bin/dataset_lookup?dataset_input_list=n8c0837su*">n8c0837su.r3h</a></td><td>FULL</td><td>ON</td><td>15</td><td>Aug 04 2003  08:33AM</td><td>INFLIGHT</td><td>11228</td><td>Aug 12 2003  03:01PM</td><td>2003/08/12</td><td>Pipeline dark: 120 frame superdark with hotpixels from 04/08/2003</td></tr>
        <tr><td><a href="http://archive.stsci.edu/cgi-bin/dataset_lookup?dataset_input_list=n8808373u*">n8808373u.r3h</a></td><td>FULL</td><td>OFF</td><td>7</td><td>Jul 28 2003  09:16AM</td><td>INFLIGHT</td><td>11228</td><td>Aug 12 2003  03:01PM</td><td>2003/08/12</td><td>Pipeline dark: 120 frame superdark with hotpixels from 28/07/2003</td></tr>
        <tr><td><a href="http://archive.stsci.edu/cgi-bin/dataset_lookup?dataset_input_list=n8808374u*">n8808374u.r3h</a></td><td>FULL</td><td>ON</td><td>7</td><td>Jul 28 2003  09:16AM</td><td>INFLIGHT</td><td>11228</td><td>Aug 12 2003  03:01PM</td><td>2003/08/12</td><td>Pipeline dark: 120 frame superdark with hotpixels from 28/07/2003</td></tr>
        <tr><td><a href="http://archive.stsci.edu/cgi-bin/dataset_lookup?dataset_input_list=n8808371u*">n8808371u.r3h</a></td><td>FULL</td><td>OFF</td><td>15</td><td>Jul 28 2003  09:16AM</td><td>INFLIGHT</td><td>11228</td><td>Aug 12 2003  03:01PM</td><td>2003/08/12</td><td>Pipeline dark: 120 frame superdark with hotpixels from 28/07/2003</td></tr>
        <tr><td><a href="http://archive.stsci.edu/cgi-bin/dataset_lookup?dataset_input_list=n8808372u*">n8808372u.r3h</a></td><td>FULL</td><td>ON</td><td>15</td><td>Jul 28 2003  09:16AM</td><td>INFLIGHT</td><td>11228</td><td>Aug 12 2003  03:01PM</td><td>2003/08/12</td><td>Pipeline dark: 120 frame superdark with hotpixels from 28/07/2003</td></tr>
        <tr><td><a href="http://archive.stsci.edu/cgi-bin/dataset_lookup?dataset_input_list=n7v0815cu*">n7v0815cu.r3h</a></td><td>FULL</td><td>OFF</td><td>7</td><td>Jul 21 2003  01:55AM</td><td>INFLIGHT</td><td>11226</td><td>Aug 06 2003  08:05PM</td><td>2003/08/07</td><td>Pipeline dark: 120 frame superdark with hotpixels from 21/07/2003</td></tr>
        <tr><td><a href="http://archive.stsci.edu/cgi-bin/dataset_lookup?dataset_input_list=n7v0815du*">n7v0815du.r3h</a></td><td>FULL</td><td>ON</td><td>7</td><td>Jul 21 2003  01:55AM</td><td>INFLIGHT</td><td>11226</td><td>Aug 06 2003  08:05PM</td><td>2003/08/07</td><td>Pipeline dark: 120 frame superdark with hotpixels from 21/07/2003</td></tr>
        <tr><td><a href="http://archive.stsci.edu/cgi-bin/dataset_lookup?dataset_input_list=n7v0815au*">n7v0815au.r3h</a></td><td>FULL</td><td>OFF</td><td>15</td><td>Jul 21 2003  01:55AM</td><td>INFLIGHT</td><td>11226</td><td>Aug 06 2003  08:05PM</td><td>2003/08/07</td><td>Pipeline dark: 120 frame superdark with hotpixels from 21/07/2003</td></tr>
        <tr><td><a href="http://archive.stsci.edu/cgi-bin/dataset_lookup?dataset_input_list=n7v0815bu*">n7v0815bu.r3h</a></td><td>FULL</td><td>ON</td><td>15</td><td>Jul 21 2003  01:55AM</td><td>INFLIGHT</td><td>11226</td><td>Aug 06 2003  08:05PM</td><td>2003/08/07</td><td>Pipeline dark: 120 frame superdark with hotpixels from 21/07/2003</td></tr>
        <tr><td><a href="http://archive.stsci.edu/cgi-bin/dataset_lookup?dataset_input_list=n7s0829mu*">n7s0829mu.r3h</a></td><td>FULL</td><td>OFF</td><td>7</td><td>Jul 14 2003  02:42AM</td><td>INFLIGHT</td><td>11226</td><td>Aug 06 2003  08:05PM</td><td>2003/08/07</td><td>Pipeline dark: 120 frame superdark with hotpixels from 14/07/2003</td></tr>
        <tr><td><a href="http://archive.stsci.edu/cgi-bin/dataset_lookup?dataset_input_list=n7s0829nu*">n7s0829nu.r3h</a></td><td>FULL</td><td>ON</td><td>7</td><td>Jul 14 2003  02:42AM</td><td>INFLIGHT</td><td>11226</td><td>Aug 06 2003  08:05PM</td><td>2003/08/07</td><td>Pipeline dark: 120 frame superdark with hotpixels from 14/07/2003</td></tr>
        <tr><td><a href="http://archive.stsci.edu/cgi-bin/dataset_lookup?dataset_input_list=n7s0829ku*">n7s0829ku.r3h</a></td><td>FULL</td><td>OFF</td><td>15</td><td>Jul 14 2003  02:42AM</td><td>INFLIGHT</td><td>11226</td><td>Aug 06 2003  08:05PM</td><td>2003/08/07</td><td>Pipeline dark: 120 frame superdark with hotpixels from 14/07/2003</td></tr>
        <tr><td><a href="http://archive.stsci.edu/cgi-bin/dataset_lookup?dataset_input_list=n7s0829lu*">n7s0829lu.r3h</a></td><td>FULL</td><td>ON</td><td>15</td><td>Jul 14 2003  02:42AM</td><td>INFLIGHT</td><td>11226</td><td>Aug 06 2003  08:05PM</td><td>2003/08/07</td><td>Pipeline dark: 120 frame superdark with hotpixels from 14/07/2003</td></tr>
        <tr><td><a href="http://archive.stsci.edu/cgi-bin/dataset_lookup?dataset_input_list=n7h0941ju*">n7h0941ju.r3h</a></td><td>FULL</td><td>OFF</td><td>7</td><td>Jul 07 2003  03:09AM</td><td>INFLIGHT</td><td>11216</td><td>Jul 17 2003  10:08PM</td><td>2003/07/18</td><td>Pipeline dark: 120 frame superdark with hotpixels from 07/07/2003</td></tr>
        <tr><td><a href="http://archive.stsci.edu/cgi-bin/dataset_lookup?dataset_input_list=n7h0941ku*">n7h0941ku.r3h</a></td><td>FULL</td><td>ON</td><td>7</td><td>Jul 07 2003  03:09AM</td><td>INFLIGHT</td><td>11216</td><td>Jul 17 2003  10:08PM</td><td>2003/07/18</td><td>Pipeline dark: 120 frame superdark with hotpixels from 07/07/2003</td></tr>
        <tr><td><a href="http://archive.stsci.edu/cgi-bin/dataset_lookup?dataset_input_list=n7h0941hu*">n7h0941hu.r3h</a></td><td>FULL</td><td>OFF</td><td>15</td><td>Jul 07 2003  03:09AM</td><td>INFLIGHT</td><td>11216</td><td>Jul 17 2003  10:08PM</td><td>2003/07/18</td><td>Pipeline dark: 120 frame superdark with hotpixels from 07/07/2003</td></tr>
        <tr><td><a href="http://archive.stsci.edu/cgi-bin/dataset_lookup?dataset_input_list=n7h0941iu*">n7h0941iu.r3h</a></td><td>FULL</td><td>ON</td><td>15</td><td>Jul 07 2003  03:09AM</td><td>INFLIGHT</td><td>11216</td><td>Jul 17 2003  10:08PM</td><td>2003/07/18</td><td>Pipeline dark: 120 frame superdark with hotpixels from 07/07/2003</td></tr>
        <tr><td><a href="http://archive.stsci.edu/cgi-bin/dataset_lookup?dataset_input_list=n7f0851ku*">n7f0851ku.r3h</a></td><td>FULL</td><td>OFF</td><td>7</td><td>Jun 30 2003  02:04AM</td><td>INFLIGHT</td><td>11216</td><td>Jul 17 2003  10:08PM</td><td>2003/07/18</td><td>Pipeline dark: 120 frame superdark with hotpixels from 30/06/2003</td></tr>
        <tr><td><a href="http://archive.stsci.edu/cgi-bin/dataset_lookup?dataset_input_list=n7f0851lu*">n7f0851lu.r3h</a></td><td>FULL</td><td>ON</td><td>7</td><td>Jun 30 2003  02:04AM</td><td>INFLIGHT</td><td>11216</td><td>Jul 17 2003  10:08PM</td><td>2003/07/18</td><td>Pipeline dark: 120 frame superdark with hotpixels from 30/06/2003</td></tr>
        <tr><td><a href="http://archive.stsci.edu/cgi-bin/dataset_lookup?dataset_input_list=n7f0851iu*">n7f0851iu.r3h</a></td><td>FULL</td><td>OFF</td><td>15</td><td>Jun 30 2003  02:04AM</td><td>INFLIGHT</td><td>11216</td><td>Jul 17 2003  10:08PM</td><td>2003/07/18</td><td>Pipeline dark: 120 frame superdark with hotpixels from 30/06/2003</td></tr>
        <tr><td><a href="http://archive.stsci.edu/cgi-bin/dataset_lookup?dataset_input_list=n7f0851ju*">n7f0851ju.r3h</a></td><td>FULL</td><td>ON</td><td>15</td><td>Jun 30 2003  02:04AM</td><td>INFLIGHT</td><td>11216</td><td>Jul 17 2003  10:08PM</td><td>2003/07/18</td><td>Pipeline dark: 120 frame superdark with hotpixels from 30/06/2003</td></tr>
        <tr><td><a href="http://archive.stsci.edu/cgi-bin/dataset_lookup?dataset_input_list=n7f0842pu*">n7f0842pu.r3h</a></td><td>FULL</td><td>OFF</td><td>7</td><td>Jun 23 2003  03:25AM</td><td>INFLIGHT</td><td>11216</td><td>Jul 17 2003  10:08PM</td><td>2003/07/18</td><td>Pipeline dark: 120 frame superdark with hotpixels from 23/06/2003</td></tr>
        <tr><td><a href="http://archive.stsci.edu/cgi-bin/dataset_lookup?dataset_input_list=n7f0842qu*">n7f0842qu.r3h</a></td><td>FULL</td><td>ON</td><td>7</td><td>Jun 23 2003  03:25AM</td><td>INFLIGHT</td><td>11216</td><td>Jul 17 2003  10:08PM</td><td>2003/07/18</td><td>Pipeline dark: 120 frame superdark with hotpixels from 23/06/2003</td></tr>
        <tr><td><a href="http://archive.stsci.edu/cgi-bin/dataset_lookup?dataset_input_list=n7f0842nu*">n7f0842nu.r3h</a></td><td>FULL</td><td>OFF</td><td>15</td><td>Jun 23 2003  03:25AM</td><td>INFLIGHT</td><td>11216</td><td>Jul 17 2003  10:08PM</td><td>2003/07/18</td><td>Pipeline dark: 120 frame superdark with hotpixels from 23/06/2003</td></tr>
        <tr><td><a href="http://archive.stsci.edu/cgi-bin/dataset_lookup?dataset_input_list=n7f0842ou*">n7f0842ou.r3h</a></td><td>FULL</td><td>ON</td><td>15</td><td>Jun 23 2003  03:25AM</td><td>INFLIGHT</td><td>11216</td><td>Jul 17 2003  10:08PM</td><td>2003/07/18</td><td>Pipeline dark: 120 frame superdark with hotpixels from 23/06/2003</td></tr>
        <tr><td><a href="http://archive.stsci.edu/cgi-bin/dataset_lookup?dataset_input_list=n6q12459u*">n6q12459u.r3h</a></td><td>FULL</td><td>OFF</td><td>7</td><td>Jun 18 2003  02:40PM</td><td>INFLIGHT</td><td>11208</td><td>Jun 26 2003  05:34PM</td><td>2003/06/26</td><td>Pipeline dark: 120 frame superdark with hotpixels from 18/06/2003</td></tr>
        <tr><td><a href="http://archive.stsci.edu/cgi-bin/dataset_lookup?dataset_input_list=n6q1245bu*">n6q1245bu.r3h</a></td><td>FULL</td><td>ON</td><td>7</td><td>Jun 18 2003  02:40PM</td><td>INFLIGHT</td><td>11208</td><td>Jun 26 2003  05:34PM</td><td>2003/06/26</td><td>Pipeline dark: 120 frame superdark with hotpixels from 18/06/2003</td></tr>
        <tr><td><a href="http://archive.stsci.edu/cgi-bin/dataset_lookup?dataset_input_list=n6q12456u*">n6q12456u.r3h</a></td><td>FULL</td><td>OFF</td><td>15</td><td>Jun 18 2003  02:40PM</td><td>INFLIGHT</td><td>11208</td><td>Jun 26 2003  05:34PM</td><td>2003/06/26</td><td>Pipeline dark: 120 frame superdark with hotpixels from 18/06/2003</td></tr>
        <tr><td><a href="http://archive.stsci.edu/cgi-bin/dataset_lookup?dataset_input_list=n6q12458u*">n6q12458u.r3h</a></td><td>FULL</td><td>ON</td><td>15</td><td>Jun 18 2003  02:40PM</td><td>INFLIGHT</td><td>11208</td><td>Jun 26 2003  05:34PM</td><td>2003/06/26</td><td>Pipeline dark: 120 frame superdark with hotpixels from 18/06/2003</td></tr>
        <tr><td><a href="http://archive.stsci.edu/cgi-bin/dataset_lookup?dataset_input_list=n6q1208tu*">n6q1208tu.r3h</a></td><td>FULL</td><td>OFF</td><td>7</td><td>Jun 16 2003  03:14PM</td><td>INFLIGHT</td><td>11208</td><td>Jun 26 2003  05:34PM</td><td>2003/06/26</td><td>Pipeline dark: 120 frame superdark with hotpixels from 16/06/2003</td></tr>
        <tr><td><a href="http://archive.stsci.edu/cgi-bin/dataset_lookup?dataset_input_list=n6q12090u*">n6q12090u.r3h</a></td><td>FULL</td><td>ON</td><td>7</td><td>Jun 16 2003  03:14PM</td><td>INFLIGHT</td><td>11208</td><td>Jun 26 2003  05:34PM</td><td>2003/06/26</td><td>Pipeline dark: 120 frame superdark with hotpixels from 16/06/2003</td></tr>
        <tr><td><a href="http://archive.stsci.edu/cgi-bin/dataset_lookup?dataset_input_list=n6q1208pu*">n6q1208pu.r3h</a></td><td>FULL</td><td>OFF</td><td>15</td><td>Jun 16 2003  03:14PM</td><td>INFLIGHT</td><td>11208</td><td>Jun 26 2003  05:34PM</td><td>2003/06/26</td><td>Pipeline dark: 120 frame superdark with hotpixels from 16/06/2003</td></tr>
        <tr><td><a href="http://archive.stsci.edu/cgi-bin/dataset_lookup?dataset_input_list=n6q1208ru*">n6q1208ru.r3h</a></td><td>FULL</td><td>ON</td><td>15</td><td>Jun 16 2003  03:14PM</td><td>INFLIGHT</td><td>11208</td><td>Jun 26 2003  05:34PM</td><td>2003/06/26</td><td>Pipeline dark: 120 frame superdark with hotpixels from 16/06/2003</td></tr>
        <tr><td><a href="http://archive.stsci.edu/cgi-bin/dataset_lookup?dataset_input_list=n6b0930su*">n6b0930su.r3h</a></td><td>FULL</td><td>OFF</td><td>7</td><td>Jun 09 2003  05:14AM</td><td>INFLIGHT</td><td>11201</td><td>Jun 11 2003  03:06PM</td><td>2003/06/11 20:44:00 GMT-4</td><td>Pipeline dark: 120 frame superdark with hotpixels from 09/06/2003</td></tr>
        <tr><td><a href="http://archive.stsci.edu/cgi-bin/dataset_lookup?dataset_input_list=n6b0930tu*">n6b0930tu.r3h</a></td><td>FULL</td><td>ON</td><td>7</td><td>Jun 09 2003  05:14AM</td><td>INFLIGHT</td><td>11201</td><td>Jun 11 2003  03:06PM</td><td>2003/06/11 20:44:00 GMT-4</td><td>Pipeline dark: 120 frame superdark with hotpixels from 09/06/2003</td></tr>
        <tr><td><a href="http://archive.stsci.edu/cgi-bin/dataset_lookup?dataset_input_list=n6b0930pu*">n6b0930pu.r3h</a></td><td>FULL</td><td>OFF</td><td>15</td><td>Jun 09 2003  05:14AM</td><td>INFLIGHT</td><td>11201</td><td>Jun 11 2003  03:06PM</td><td>2003/06/11 20:44:00 GMT-4</td><td>Pipeline dark: 120 frame superdark with hotpixels from 09/06/2003</td></tr>
        <tr><td><a href="http://archive.stsci.edu/cgi-bin/dataset_lookup?dataset_input_list=n6b0930qu*">n6b0930qu.r3h</a></td><td>FULL</td><td>ON</td><td>15</td><td>Jun 09 2003  05:14AM</td><td>INFLIGHT</td><td>11201</td><td>Jun 11 2003  03:06PM</td><td>2003/06/11 20:44:00 GMT-4</td><td>Pipeline dark: 120 frame superdark with hotpixels from 09/06/2003</td></tr>
        <tr><td><a href="http://archive.stsci.edu/cgi-bin/dataset_lookup?dataset_input_list=n641044gu*">n641044gu.r3h</a></td><td>FULL</td><td>OFF</td><td>7</td><td>Jun 02 2003  01:50AM</td><td>INFLIGHT</td><td>11198</td><td>Jun 04 2003  03:00PM</td><td>2003/06/04 16:13:00 GMT-4</td><td>Pipeline dark: 120 frame superdark with hotpixels from 02/06/2003</td></tr>
        <tr><td><a href="http://archive.stsci.edu/cgi-bin/dataset_lookup?dataset_input_list=n641044hu*">n641044hu.r3h</a></td><td>FULL</td><td>ON</td><td>7</td><td>Jun 02 2003  01:50AM</td><td>INFLIGHT</td><td>11198</td><td>Jun 04 2003  03:00PM</td><td>2003/06/04 16:13:00 GMT-4</td><td>Pipeline dark: 120 frame superdark with hotpixels from 02/06/2003</td></tr>
        <tr><td><a href="http://archive.stsci.edu/cgi-bin/dataset_lookup?dataset_input_list=n641044eu*">n641044eu.r3h</a></td><td>FULL</td><td>OFF</td><td>15</td><td>Jun 02 2003  01:50AM</td><td>INFLIGHT</td><td>11198</td><td>Jun 04 2003  03:00PM</td><td>2003/06/04 16:13:00 GMT-4</td><td>Pipeline dark: 120 frame superdark with hotpixels from 02/06/2003</td></tr>
        <tr><td><a href="http://archive.stsci.edu/cgi-bin/dataset_lookup?dataset_input_list=n641044fu*">n641044fu.r3h</a></td><td>FULL</td><td>ON</td><td>15</td><td>Jun 02 2003  01:50AM</td><td>INFLIGHT</td><td>11198</td><td>Jun 04 2003  03:00PM</td><td>2003/06/04 16:13:00 GMT-4</td><td>Pipeline dark: 120 frame superdark with hotpixels from 02/06/2003</td></tr>
        <tr><td><a href="http://archive.stsci.edu/cgi-bin/dataset_lookup?dataset_input_list=n5u0907qu*">n5u0907qu.r3h</a></td><td>FULL</td><td>OFF</td><td>7</td><td>May 26 2003  04:35AM</td><td>INFLIGHT</td><td>11197</td><td>Jun 03 2003  02:57PM</td><td>2003/06/03 16:17:00 GMT-4</td><td>Pipeline dark: 120 frame superdark with hotpixels from 26/05/2003</td></tr>
        <tr><td><a href="http://archive.stsci.edu/cgi-bin/dataset_lookup?dataset_input_list=n5u0907ru*">n5u0907ru.r3h</a></td><td>FULL</td><td>ON</td><td>7</td><td>May 26 2003  04:35AM</td><td>INFLIGHT</td><td>11197</td><td>Jun 03 2003  02:57PM</td><td>2003/06/03 16:17:00 GMT-4</td><td>Pipeline dark: 120 frame superdark with hotpixels from 26/05/2003</td></tr>
        <tr><td><a href="http://archive.stsci.edu/cgi-bin/dataset_lookup?dataset_input_list=n5u0907ou*">n5u0907ou.r3h</a></td><td>FULL</td><td>OFF</td><td>15</td><td>May 26 2003  04:35AM</td><td>INFLIGHT</td><td>11197</td><td>Jun 03 2003  02:57PM</td><td>2003/06/03 16:17:00 GMT-4</td><td>Pipeline dark: 120 frame superdark with hotpixels from 26/05/2003</td></tr>
        <tr><td><a href="http://archive.stsci.edu/cgi-bin/dataset_lookup?dataset_input_list=n5u0907pu*">n5u0907pu.r3h</a></td><td>FULL</td><td>ON</td><td>15</td><td>May 26 2003  04:35AM</td><td>INFLIGHT</td><td>11197</td><td>Jun 03 2003  02:57PM</td><td>2003/06/03 16:17:00 GMT-4</td><td>Pipeline dark: 120 frame superdark with hotpixels from 26/05/2003</td></tr>
        <tr><td><a href="http://archive.stsci.edu/cgi-bin/dataset_lookup?dataset_input_list=n5j09036u*">n5j09036u.r3h</a></td><td>FULL</td><td>OFF</td><td>7</td><td>May 19 2003  02:37AM</td><td>INFLIGHT</td><td>11192</td><td>May 19 2003  02:23PM</td><td>2003/05/19 16:08:00 GMT-4</td><td>Pipeline dark: 120 frame superdark with hotpixels from 19/05/2003</td></tr>
        <tr><td><a href="http://archive.stsci.edu/cgi-bin/dataset_lookup?dataset_input_list=n5j09037u*">n5j09037u.r3h</a></td><td>FULL</td><td>ON</td><td>7</td><td>May 19 2003  02:37AM</td><td>INFLIGHT</td><td>11192</td><td>May 19 2003  02:23PM</td><td>2003/05/19 16:08:00 GMT-4</td><td>Pipeline dark: 120 frame superdark with hotpixels from 19/05/2003</td></tr>
        <tr><td><a href="http://archive.stsci.edu/cgi-bin/dataset_lookup?dataset_input_list=n5j09034u*">n5j09034u.r3h</a></td><td>FULL</td><td>OFF</td><td>15</td><td>May 19 2003  02:37AM</td><td>INFLIGHT</td><td>11192</td><td>May 19 2003  02:23PM</td><td>2003/05/19 16:08:00 GMT-4</td><td>Pipeline dark: 120 frame superdark with hotpixels from 19/05/2003</td></tr>
        <tr><td><a href="http://archive.stsci.edu/cgi-bin/dataset_lookup?dataset_input_list=n5j09035u*">n5j09035u.r3h</a></td><td>FULL</td><td>ON</td><td>15</td><td>May 19 2003  02:37AM</td><td>INFLIGHT</td><td>11192</td><td>May 19 2003  02:23PM</td><td>2003/05/19 16:08:00 GMT-4</td><td>Pipeline dark: 120 frame superdark with hotpixels from 19/05/2003</td></tr>
        <tr><td><a href="http://archive.stsci.edu/cgi-bin/dataset_lookup?dataset_input_list=n5j0842cu*">n5j0842cu.r3h</a></td><td>FULL</td><td>OFF</td><td>7</td><td>May 12 2003  02:33AM</td><td>INFLIGHT</td><td>11192</td><td>May 19 2003  02:23PM</td><td>2003/05/19 16:08:00 GMT-4</td><td>Pipeline dark: 120 frame superdark with hotpixels from 12/05/2003</td></tr>
        <tr><td><a href="http://archive.stsci.edu/cgi-bin/dataset_lookup?dataset_input_list=n5j0842du*">n5j0842du.r3h</a></td><td>FULL</td><td>ON</td><td>7</td><td>May 12 2003  02:33AM</td><td>INFLIGHT</td><td>11192</td><td>May 19 2003  02:23PM</td><td>2003/05/19 16:08:00 GMT-4</td><td>Pipeline dark: 120 frame superdark with hotpixels from 12/05/2003</td></tr>
        <tr><td><a href="http://archive.stsci.edu/cgi-bin/dataset_lookup?dataset_input_list=n5j0842au*">n5j0842au.r3h</a></td><td>FULL</td><td>OFF</td><td>15</td><td>May 12 2003  02:33AM</td><td>INFLIGHT</td><td>11192</td><td>May 19 2003  02:23PM</td><td>2003/05/19 16:08:00 GMT-4</td><td>Pipeline dark: 120 frame superdark with hotpixels from 12/05/2003</td></tr>
        <tr><td><a href="http://archive.stsci.edu/cgi-bin/dataset_lookup?dataset_input_list=n5j0842bu*">n5j0842bu.r3h</a></td><td>FULL</td><td>ON</td><td>15</td><td>May 12 2003  02:33AM</td><td>INFLIGHT</td><td>11192</td><td>May 19 2003  02:23PM</td><td>2003/05/19 16:08:00 GMT-4</td><td>Pipeline dark: 120 frame superdark with hotpixels from 12/05/2003</td></tr>
        <tr><td><a href="http://archive.stsci.edu/cgi-bin/dataset_lookup?dataset_input_list=n571432cu*">n571432cu.r3h</a></td><td>FULL</td><td>OFF</td><td>7</td><td>May 05 2003  04:00AM</td><td>INFLIGHT</td><td>11190</td><td>May 13 2003  04:07PM</td><td>2003/05/13 17:30:00 GMT-4</td><td>Pipeline dark: 120 frame superdark with hotpixels from 05/05/2003</td></tr>
        <tr><td><a href="http://archive.stsci.edu/cgi-bin/dataset_lookup?dataset_input_list=n571432du*">n571432du.r3h</a></td><td>FULL</td><td>ON</td><td>7</td><td>May 05 2003  04:00AM</td><td>INFLIGHT</td><td>11190</td><td>May 13 2003  04:07PM</td><td>2003/05/13 17:30:00 GMT-4</td><td>Pipeline dark: 120 frame superdark with hotpixels from 05/05/2003</td></tr>
        <tr><td><a href="http://archive.stsci.edu/cgi-bin/dataset_lookup?dataset_input_list=n571432au*">n571432au.r3h</a></td><td>FULL</td><td>OFF</td><td>15</td><td>May 05 2003  04:00AM</td><td>INFLIGHT</td><td>11190</td><td>May 13 2003  04:07PM</td><td>2003/05/13 17:30:00 GMT-4</td><td>Pipeline dark: 120 frame superdark with hotpixels from 05/05/2003</td></tr>
        <tr><td><a href="http://archive.stsci.edu/cgi-bin/dataset_lookup?dataset_input_list=n571432bu*">n571432bu.r3h</a></td><td>FULL</td><td>ON</td><td>15</td><td>May 05 2003  04:00AM</td><td>INFLIGHT</td><td>11190</td><td>May 13 2003  04:07PM</td><td>2003/05/13 17:30:00 GMT-4</td><td>Pipeline dark: 120 frame superdark with hotpixels from 05/05/2003</td></tr>
        <tr><td><a href="http://archive.stsci.edu/cgi-bin/dataset_lookup?dataset_input_list=n5510087u*">n5510087u.r3h</a></td><td>FULL</td><td>OFF</td><td>7</td><td>May 01 2003  03:54PM</td><td>INFLIGHT</td><td>11188</td><td>May 06 2003  05:27PM</td><td>2003/05/06 18:57:00 GMT-4</td><td>Pipeline dark: 120 frame superdark with hotpixels from 01/05/2003</td></tr>
        <tr><td><a href="http://archive.stsci.edu/cgi-bin/dataset_lookup?dataset_input_list=n5510088u*">n5510088u.r3h</a></td><td>FULL</td><td>ON</td><td>7</td><td>May 01 2003  03:54PM</td><td>INFLIGHT</td><td>11188</td><td>May 06 2003  05:27PM</td><td>2003/05/06 18:57:00 GMT-4</td><td>Pipeline dark: 120 frame superdark with hotpixels from 01/05/2003</td></tr>
        <tr><td><a href="http://archive.stsci.edu/cgi-bin/dataset_lookup?dataset_input_list=n5510085u*">n5510085u.r3h</a></td><td>FULL</td><td>OFF</td><td>15</td><td>May 01 2003  03:54PM</td><td>INFLIGHT</td><td>11188</td><td>May 06 2003  05:27PM</td><td>2003/05/06 18:57:00 GMT-4</td><td>Pipeline dark: 120 frame superdark with hotpixels from 01/05/2003</td></tr>
        <tr><td><a href="http://archive.stsci.edu/cgi-bin/dataset_lookup?dataset_input_list=n5510086u*">n5510086u.r3h</a></td><td>FULL</td><td>ON</td><td>15</td><td>May 01 2003  03:54PM</td><td>INFLIGHT</td><td>11188</td><td>May 06 2003  05:27PM</td><td>2003/05/06 18:57:00 GMT-4</td><td>Pipeline dark: 120 frame superdark with hotpixels from 01/05/2003</td></tr>
        <tr><td><a href="http://archive.stsci.edu/cgi-bin/dataset_lookup?dataset_input_list=n5510002u*">n5510002u.r3h</a></td><td>FULL</td><td>OFF</td><td>7</td><td>Apr 28 2003  09:18AM</td><td>INFLIGHT</td><td>11188</td><td>May 06 2003  05:27PM</td><td>2003/05/06 18:57:00 GMT-4</td><td>Pipeline dark: 120 frame superdark with hotpixels from 28/04/2003</td></tr>
        <tr><td><a href="http://archive.stsci.edu/cgi-bin/dataset_lookup?dataset_input_list=n5510003u*">n5510003u.r3h</a></td><td>FULL</td><td>ON</td><td>7</td><td>Apr 28 2003  09:18AM</td><td>INFLIGHT</td><td>11188</td><td>May 06 2003  05:27PM</td><td>2003/05/06 18:57:00 GMT-4</td><td>Pipeline dark: 120 frame superdark with hotpixels from 28/04/2003</td></tr>
        <tr><td><a href="http://archive.stsci.edu/cgi-bin/dataset_lookup?dataset_input_list=n5510000u*">n5510000u.r3h</a></td><td>FULL</td><td>OFF</td><td>15</td><td>Apr 28 2003  09:18AM</td><td>INFLIGHT</td><td>11188</td><td>May 06 2003  05:27PM</td><td>2003/05/06 18:57:00 GMT-4</td><td>Pipeline dark: 120 frame superdark with hotpixels from 28/04/2003</td></tr>
        <tr><td><a href="http://archive.stsci.edu/cgi-bin/dataset_lookup?dataset_input_list=n5510001u*">n5510001u.r3h</a></td><td>FULL</td><td>ON</td><td>15</td><td>Apr 28 2003  09:18AM</td><td>INFLIGHT</td><td>11188</td><td>May 06 2003  05:27PM</td><td>2003/05/06 18:57:00 GMT-4</td><td>Pipeline dark: 120 frame superdark with hotpixels from 28/04/2003</td></tr>
        <tr><td><a href="http://archive.stsci.edu/cgi-bin/dataset_lookup?dataset_input_list=n4p1330ju*">n4p1330ju.r3h</a></td><td>FULL</td><td>OFF</td><td>7</td><td>Apr 21 2003  02:07AM</td><td>INFLIGHT</td><td>11185</td><td>Apr 28 2003  01:33PM</td><td>2003/04/28 14:56:00 GMT-4</td><td>Pipeline dark: 120 frame superdark with hotpixels from 21/04/2003</td></tr>
        <tr><td><a href="http://archive.stsci.edu/cgi-bin/dataset_lookup?dataset_input_list=n4p1330ku*">n4p1330ku.r3h</a></td><td>FULL</td><td>ON</td><td>7</td><td>Apr 21 2003  02:07AM</td><td>INFLIGHT</td><td>11185</td><td>Apr 28 2003  01:33PM</td><td>2003/04/28 14:56:00 GMT-4</td><td>Pipeline dark: 120 frame superdark with hotpixels from 21/04/2003</td></tr>
        <tr><td><a href="http://archive.stsci.edu/cgi-bin/dataset_lookup?dataset_input_list=n4p13308u*">n4p13308u.r3h</a></td><td>FULL</td><td>OFF</td><td>15</td><td>Apr 21 2003  02:07AM</td><td>INFLIGHT</td><td>11185</td><td>Apr 28 2003  01:33PM</td><td>2003/04/28 14:56:00 GMT-4</td><td>Pipeline dark: 120 frame superdark with hotpixels from 21/04/2003</td></tr>
        <tr><td><a href="http://archive.stsci.edu/cgi-bin/dataset_lookup?dataset_input_list=n4p1330iu*">n4p1330iu.r3h</a></td><td>FULL</td><td>ON</td><td>15</td><td>Apr 21 2003  02:07AM</td><td>INFLIGHT</td><td>11185</td><td>Apr 28 2003  01:33PM</td><td>2003/04/28 14:56:00 GMT-4</td><td>Pipeline dark: 120 frame superdark with hotpixels from 21/04/2003</td></tr>
        <tr><td><a href="http://archive.stsci.edu/cgi-bin/dataset_lookup?dataset_input_list=n4l08400u*">n4l08400u.r3h</a></td><td>FULL</td><td>OFF</td><td>7</td><td>Apr 07 2003  01:41AM</td><td>INFLIGHT</td><td>11183</td><td>Apr 23 2003  02:22PM</td><td>2003/04/23 16:05:00 GMT-4</td><td>Pipeline dark: 120 frame superdark with hotpixels from 07/04/2003</td></tr>
        <tr><td><a href="http://archive.stsci.edu/cgi-bin/dataset_lookup?dataset_input_list=n4l08401u*">n4l08401u.r3h</a></td><td>FULL</td><td>ON</td><td>7</td><td>Apr 07 2003  01:41AM</td><td>INFLIGHT</td><td>11183</td><td>Apr 23 2003  02:22PM</td><td>2003/04/23 16:05:00 GMT-4</td><td>Pipeline dark: 120 frame superdark with hotpixels from 07/04/2003</td></tr>
        <tr><td><a href="http://archive.stsci.edu/cgi-bin/dataset_lookup?dataset_input_list=n4l0839su*">n4l0839su.r3h</a></td><td>FULL</td><td>OFF</td><td>15</td><td>Apr 07 2003  01:41AM</td><td>INFLIGHT</td><td>11183</td><td>Apr 23 2003  02:22PM</td><td>2003/04/23 16:05:00 GMT-4</td><td>Pipeline dark: 120 frame superdark with hotpixels from 07/04/2003</td></tr>
        <tr><td><a href="http://archive.stsci.edu/cgi-bin/dataset_lookup?dataset_input_list=n4l0839tu*">n4l0839tu.r3h</a></td><td>FULL</td><td>ON</td><td>15</td><td>Apr 07 2003  01:41AM</td><td>INFLIGHT</td><td>11183</td><td>Apr 23 2003  02:22PM</td><td>2003/04/23 16:05:00 GMT-4</td><td>Pipeline dark: 120 frame superdark with hotpixels from 07/04/2003</td></tr>
        <tr><td><a href="http://archive.stsci.edu/cgi-bin/dataset_lookup?dataset_input_list=n491502ju*">n491502ju.r3h</a></td><td>FULL</td><td>OFF</td><td>7</td><td>Mar 31 2003  01:49AM</td><td>INFLIGHT</td><td>11180</td><td>Apr 15 2003  06:30PM</td><td>2003/04/15 19:26:00 GMT-4</td><td>Pipeline dark: 120 frame superdark with hotpixels from 31/03/2003</td></tr>
        <tr><td><a href="http://archive.stsci.edu/cgi-bin/dataset_lookup?dataset_input_list=n491502ku*">n491502ku.r3h</a></td><td>FULL</td><td>ON</td><td>7</td><td>Mar 31 2003  01:49AM</td><td>INFLIGHT</td><td>11180</td><td>Apr 15 2003  06:30PM</td><td>2003/04/15 19:26:00 GMT-4</td><td>Pipeline dark: 120 frame superdark with hotpixels from 31/03/2003</td></tr>
        <tr><td><a href="http://archive.stsci.edu/cgi-bin/dataset_lookup?dataset_input_list=n491502hu*">n491502hu.r3h</a></td><td>FULL</td><td>OFF</td><td>15</td><td>Mar 31 2003  01:49AM</td><td>INFLIGHT</td><td>11180</td><td>Apr 15 2003  06:30PM</td><td>2003/04/15 19:26:00 GMT-4</td><td>Pipeline dark: 120 frame superdark with hotpixels from 31/03/2003</td></tr>
        <tr><td><a href="http://archive.stsci.edu/cgi-bin/dataset_lookup?dataset_input_list=n491502iu*">n491502iu.r3h</a></td><td>FULL</td><td>ON</td><td>15</td><td>Mar 31 2003  01:49AM</td><td>INFLIGHT</td><td>11180</td><td>Apr 15 2003  06:30PM</td><td>2003/04/15 19:26:00 GMT-4</td><td>Pipeline dark: 120 frame superdark with hotpixels from 31/03/2003</td></tr>
        <tr><td><a href="http://archive.stsci.edu/cgi-bin/dataset_lookup?dataset_input_list=n470909nu*">n470909nu.r3h</a></td><td>FULL</td><td>OFF</td><td>7</td><td>Mar 24 2003  03:04AM</td><td>INFLIGHT</td><td>11177</td><td>Apr 07 2003  01:57PM</td><td>2003/04/07 14:58:00 GMT-4</td><td>Pipeline dark: 120 frame superdark with hotpixels from 24/03/2003</td></tr>
        <tr><td><a href="http://archive.stsci.edu/cgi-bin/dataset_lookup?dataset_input_list=n470909ou*">n470909ou.r3h</a></td><td>FULL</td><td>ON</td><td>7</td><td>Mar 24 2003  03:04AM</td><td>INFLIGHT</td><td>11177</td><td>Apr 07 2003  01:57PM</td><td>2003/04/07 14:58:00 GMT-4</td><td>Pipeline dark: 120 frame superdark with hotpixels from 24/03/2003</td></tr>
        <tr><td><a href="http://archive.stsci.edu/cgi-bin/dataset_lookup?dataset_input_list=n470909lu*">n470909lu.r3h</a></td><td>FULL</td><td>OFF</td><td>15</td><td>Mar 24 2003  03:04AM</td><td>INFLIGHT</td><td>11177</td><td>Apr 07 2003  01:57PM</td><td>2003/04/07 14:58:00 GMT-4</td><td>Pipeline dark: 120 frame superdark with hotpixels from 24/03/2003</td></tr>
        <tr><td><a href="http://archive.stsci.edu/cgi-bin/dataset_lookup?dataset_input_list=n470909mu*">n470909mu.r3h</a></td><td>FULL</td><td>ON</td><td>15</td><td>Mar 24 2003  03:04AM</td><td>INFLIGHT</td><td>11177</td><td>Apr 07 2003  01:57PM</td><td>2003/04/07 14:58:00 GMT-4</td><td>Pipeline dark: 120 frame superdark with hotpixels from 24/03/2003</td></tr>
        <tr><td><a href="http://archive.stsci.edu/cgi-bin/dataset_lookup?dataset_input_list=n3j1037cu*">n3j1037cu.r3h</a></td><td>FULL</td><td>OFF</td><td>7</td><td>Mar 13 2003  08:43AM</td><td>INFLIGHT</td><td>11168</td><td>Mar 19 2003  04:49PM</td><td>2003/03/28 20:55:00 US/Eastern</td><td>Pipeline dark: 120 frame superdark with hotpixels from 13/03/2003</td></tr>
        <tr><td><a href="http://archive.stsci.edu/cgi-bin/dataset_lookup?dataset_input_list=n3j1037du*">n3j1037du.r3h</a></td><td>FULL</td><td>ON</td><td>7</td><td>Mar 13 2003  08:43AM</td><td>INFLIGHT</td><td>11168</td><td>Mar 19 2003  04:49PM</td><td>2003/03/28 20:55:00 US/Eastern</td><td>Pipeline dark: 120 frame superdark with hotpixels from 13/03/2003</td></tr>
        <tr><td><a href="http://archive.stsci.edu/cgi-bin/dataset_lookup?dataset_input_list=n3j10379u*">n3j10379u.r3h</a></td><td>FULL</td><td>OFF</td><td>15</td><td>Mar 13 2003  08:43AM</td><td>INFLIGHT</td><td>11168</td><td>Mar 19 2003  04:49PM</td><td>2003/03/28 20:55:00 US/Eastern</td><td>Pipeline dark: 120 frame superdark with hotpixels from 13/03/2003</td></tr>
        <tr><td><a href="http://archive.stsci.edu/cgi-bin/dataset_lookup?dataset_input_list=n3j1037bu*">n3j1037bu.r3h</a></td><td>FULL</td><td>ON</td><td>15</td><td>Mar 13 2003  08:43AM</td><td>INFLIGHT</td><td>11168</td><td>Mar 19 2003  04:49PM</td><td>2003/03/28 20:55:00 US/Eastern</td><td>Pipeline dark: 120 frame superdark with hotpixels from 13/03/2003</td></tr>
        <tr><td><a href="http://archive.stsci.edu/cgi-bin/dataset_lookup?dataset_input_list=n3j1021cu*">n3j1021cu.r3h</a></td><td>FULL</td><td>OFF</td><td>7</td><td>Mar 12 2003  10:10AM</td><td>INFLIGHT</td><td>11168</td><td>Mar 19 2003  04:49PM</td><td>2003/03/28 20:55:00 US/Eastern</td><td>Pipeline dark: 120 frame superdark with hotpixels from 12/03/2003</td></tr>
        <tr><td><a href="http://archive.stsci.edu/cgi-bin/dataset_lookup?dataset_input_list=n3j1021du*">n3j1021du.r3h</a></td><td>FULL</td><td>ON</td><td>7</td><td>Mar 12 2003  10:10AM</td><td>INFLIGHT</td><td>11168</td><td>Mar 19 2003  04:49PM</td><td>2003/03/28 20:55:00 US/Eastern</td><td>Pipeline dark: 120 frame superdark with hotpixels from 12/03/2003</td></tr>
        <tr><td><a href="http://archive.stsci.edu/cgi-bin/dataset_lookup?dataset_input_list=n3j10219u*">n3j10219u.r3h</a></td><td>FULL</td><td>OFF</td><td>15</td><td>Mar 12 2003  10:10AM</td><td>INFLIGHT</td><td>11168</td><td>Mar 19 2003  04:49PM</td><td>2003/03/28 20:55:00 US/Eastern</td><td>Pipeline dark: 120 frame superdark with hotpixels from 12/03/2003</td></tr>
        <tr><td><a href="http://archive.stsci.edu/cgi-bin/dataset_lookup?dataset_input_list=n3j1021bu*">n3j1021bu.r3h</a></td><td>FULL</td><td>ON</td><td>15</td><td>Mar 12 2003  10:10AM</td><td>INFLIGHT</td><td>11168</td><td>Mar 19 2003  04:49PM</td><td>2003/03/28 20:55:00 US/Eastern</td><td>Pipeline dark: 120 frame superdark with hotpixels from 12/03/2003</td></tr>
        <tr><td><a href="http://archive.stsci.edu/cgi-bin/dataset_lookup?dataset_input_list=n3j0944lu*">n3j0944lu.r3h</a></td><td>FULL</td><td>OFF</td><td>7</td><td>Mar 03 2003  02:52AM</td><td>INFLIGHT</td><td>11168</td><td>Mar 19 2003  04:49PM</td><td>2003/03/28 20:55:00 US/Eastern</td><td>Pipeline dark: 120 frame superdark with hotpixels from 03/03/2003</td></tr>
        <tr><td><a href="http://archive.stsci.edu/cgi-bin/dataset_lookup?dataset_input_list=n3j0944mu*">n3j0944mu.r3h</a></td><td>FULL</td><td>ON</td><td>7</td><td>Mar 03 2003  02:52AM</td><td>INFLIGHT</td><td>11168</td><td>Mar 19 2003  04:49PM</td><td>2003/03/28 20:55:00 US/Eastern</td><td>Pipeline dark: 120 frame superdark with hotpixels from 03/03/2003</td></tr>
        <tr><td><a href="http://archive.stsci.edu/cgi-bin/dataset_lookup?dataset_input_list=n3j0944hu*">n3j0944hu.r3h</a></td><td>FULL</td><td>OFF</td><td>15</td><td>Mar 03 2003  02:52AM</td><td>INFLIGHT</td><td>11168</td><td>Mar 19 2003  04:49PM</td><td>2003/03/28 20:55:00 US/Eastern</td><td>Pipeline dark: 120 frame superdark with hotpixels from 03/03/2003</td></tr>
        <tr><td><a href="http://archive.stsci.edu/cgi-bin/dataset_lookup?dataset_input_list=n3j0944ku*">n3j0944ku.r3h</a></td><td>FULL</td><td>ON</td><td>15</td><td>Mar 03 2003  02:52AM</td><td>INFLIGHT</td><td>11168</td><td>Mar 19 2003  04:49PM</td><td>2003/03/28 20:55:00 US/Eastern</td><td>Pipeline dark: 120 frame superdark with hotpixels from 03/03/2003</td></tr>
        <tr><td><a href="http://archive.stsci.edu/cgi-bin/dataset_lookup?dataset_input_list=n2r1135gu*">n2r1135gu.r3h</a></td><td>FULL</td><td>OFF</td><td>7</td><td>Feb 24 2003  01:08AM</td><td>INFLIGHT</td><td>11156</td><td>Mar 03 2003  07:56PM</td><td>2003/03/03 21:53:00 US/Eastern</td><td>Pipeline dark: 120 frame superdark with hotpixels from 24/02/2003</td></tr>
        <tr><td><a href="http://archive.stsci.edu/cgi-bin/dataset_lookup?dataset_input_list=n2r1135hu*">n2r1135hu.r3h</a></td><td>FULL</td><td>ON</td><td>7</td><td>Feb 24 2003  01:08AM</td><td>INFLIGHT</td><td>11156</td><td>Mar 03 2003  07:56PM</td><td>2003/03/03 21:53:00 US/Eastern</td><td>Pipeline dark: 120 frame superdark with hotpixels from 24/02/2003</td></tr>
        <tr><td><a href="http://archive.stsci.edu/cgi-bin/dataset_lookup?dataset_input_list=n2r1135eu*">n2r1135eu.r3h</a></td><td>FULL</td><td>OFF</td><td>15</td><td>Feb 24 2003  01:08AM</td><td>INFLIGHT</td><td>11156</td><td>Mar 03 2003  07:56PM</td><td>2003/03/03 21:53:00 US/Eastern</td><td>Pipeline dark: 120 frame superdark with hotpixels from 24/02/2003</td></tr>
        <tr><td><a href="http://archive.stsci.edu/cgi-bin/dataset_lookup?dataset_input_list=n2r1135fu*">n2r1135fu.r3h</a></td><td>FULL</td><td>ON</td><td>15</td><td>Feb 24 2003  01:08AM</td><td>INFLIGHT</td><td>11156</td><td>Mar 03 2003  07:56PM</td><td>2003/03/03 21:53:00 US/Eastern</td><td>Pipeline dark: 120 frame superdark with hotpixels from 24/02/2003</td></tr>
        <tr><td><a href="http://archive.stsci.edu/cgi-bin/dataset_lookup?dataset_input_list=n2q0901au*">n2q0901au.r3h</a></td><td>FULL</td><td>OFF</td><td>7</td><td>Feb 17 2003  01:13AM</td><td>INFLIGHT</td><td>11156</td><td>Mar 03 2003  07:56PM</td><td>2003/03/03 21:53:00 US/Eastern</td><td>Pipeline dark: 120 frame superdark with hotpixels from 17/02/2003</td></tr>
        <tr><td><a href="http://archive.stsci.edu/cgi-bin/dataset_lookup?dataset_input_list=n2q0901bu*">n2q0901bu.r3h</a></td><td>FULL</td><td>ON</td><td>7</td><td>Feb 17 2003  01:13AM</td><td>INFLIGHT</td><td>11156</td><td>Mar 03 2003  07:56PM</td><td>2003/03/03 21:53:00 US/Eastern</td><td>Pipeline dark: 120 frame superdark with hotpixels from 17/02/2003</td></tr>
        <tr><td><a href="http://archive.stsci.edu/cgi-bin/dataset_lookup?dataset_input_list=n2q09018u*">n2q09018u.r3h</a></td><td>FULL</td><td>OFF</td><td>15</td><td>Feb 17 2003  01:13AM</td><td>INFLIGHT</td><td>11156</td><td>Mar 03 2003  07:56PM</td><td>2003/03/03 21:53:00 US/Eastern</td><td>Pipeline dark: 120 frame superdark with hotpixels from 17/02/2003</td></tr>
        <tr><td><a href="http://archive.stsci.edu/cgi-bin/dataset_lookup?dataset_input_list=n2q09019u*">n2q09019u.r3h</a></td><td>FULL</td><td>ON</td><td>15</td><td>Feb 17 2003  01:13AM</td><td>INFLIGHT</td><td>11156</td><td>Mar 03 2003  07:56PM</td><td>2003/03/03 21:53:00 US/Eastern</td><td>Pipeline dark: 120 frame superdark with hotpixels from 17/02/2003</td></tr>
        <tr><td><a href="http://archive.stsci.edu/cgi-bin/dataset_lookup?dataset_input_list=n2k1200hu*">n2k1200hu.r3h</a></td><td>FULL</td><td>OFF</td><td>7</td><td>Feb 13 2003  05:59AM</td><td>INFLIGHT</td><td>11152</td><td>Feb 24 2003  09:06PM</td><td>2003/02/25 17:17:00 US/Eastern</td><td>Pipeline dark: 120 frame superdark with hotpixels from 13/02/2003</td></tr>
        <tr><td><a href="http://archive.stsci.edu/cgi-bin/dataset_lookup?dataset_input_list=n2k1200iu*">n2k1200iu.r3h</a></td><td>FULL</td><td>ON</td><td>7</td><td>Feb 13 2003  05:59AM</td><td>INFLIGHT</td><td>11152</td><td>Feb 24 2003  09:06PM</td><td>2003/02/25 17:17:00 US/Eastern</td><td>Pipeline dark: 120 frame superdark with hotpixels from 13/02/2003</td></tr>
        <tr><td><a href="http://archive.stsci.edu/cgi-bin/dataset_lookup?dataset_input_list=n2k1200fu*">n2k1200fu.r3h</a></td><td>FULL</td><td>OFF</td><td>15</td><td>Feb 13 2003  05:59AM</td><td>INFLIGHT</td><td>11152</td><td>Feb 24 2003  09:06PM</td><td>2003/02/25 17:17:00 US/Eastern</td><td>Pipeline dark: 120 frame superdark with hotpixels from 13/02/2003</td></tr>
        <tr><td><a href="http://archive.stsci.edu/cgi-bin/dataset_lookup?dataset_input_list=n2k1200gu*">n2k1200gu.r3h</a></td><td>FULL</td><td>ON</td><td>15</td><td>Feb 13 2003  05:59AM</td><td>INFLIGHT</td><td>11152</td><td>Feb 24 2003  09:06PM</td><td>2003/02/25 17:17:00 US/Eastern</td><td>Pipeline dark: 120 frame superdark with hotpixels from 13/02/2003</td></tr>
        <tr><td><a href="http://archive.stsci.edu/cgi-bin/dataset_lookup?dataset_input_list=n2k1015tu*">n2k1015tu.r3h</a></td><td>FULL</td><td>OFF</td><td>7</td><td>Feb 11 2003  12:15AM</td><td>INFLIGHT</td><td>11152</td><td>Feb 24 2003  09:06PM</td><td>2003/02/25 17:17:00 US/Eastern</td><td>Pipeline dark: 120 frame superdark with hotpixels from 11/02/2003</td></tr>
        <tr><td><a href="http://archive.stsci.edu/cgi-bin/dataset_lookup?dataset_input_list=n2k10160u*">n2k10160u.r3h</a></td><td>FULL</td><td>ON</td><td>7</td><td>Feb 11 2003  12:15AM</td><td>INFLIGHT</td><td>11152</td><td>Feb 24 2003  09:06PM</td><td>2003/02/25 17:17:00 US/Eastern</td><td>Pipeline dark: 120 frame superdark with hotpixels from 11/02/2003</td></tr>
        <tr><td><a href="http://archive.stsci.edu/cgi-bin/dataset_lookup?dataset_input_list=n2k1015ru*">n2k1015ru.r3h</a></td><td>FULL</td><td>OFF</td><td>15</td><td>Feb 11 2003  12:15AM</td><td>INFLIGHT</td><td>11152</td><td>Feb 24 2003  09:06PM</td><td>2003/02/25 17:17:00 US/Eastern</td><td>Pipeline dark: 120 frame superdark with hotpixels from 11/02/2003</td></tr>
        <tr><td><a href="http://archive.stsci.edu/cgi-bin/dataset_lookup?dataset_input_list=n2k1015su*">n2k1015su.r3h</a></td><td>FULL</td><td>ON</td><td>15</td><td>Feb 11 2003  12:15AM</td><td>INFLIGHT</td><td>11152</td><td>Feb 24 2003  09:06PM</td><td>2003/02/25 17:17:00 US/Eastern</td><td>Pipeline dark: 120 frame superdark with hotpixels from 11/02/2003</td></tr>
        <tr><td><a href="http://archive.stsci.edu/cgi-bin/dataset_lookup?dataset_input_list=n271647eu*">n271647eu.r3h</a></td><td>FULL</td><td>OFF</td><td>7</td><td>Feb 03 2003  01:59AM</td><td>INFLIGHT</td><td>11146</td><td>Feb 12 2003  09:53PM</td><td>2003/02/13 14:56:00 US/Eastern</td><td>Pipeline dark: 120 frame superdark with hotpixels from 03/02/2003</td></tr>
        <tr><td><a href="http://archive.stsci.edu/cgi-bin/dataset_lookup?dataset_input_list=n271647fu*">n271647fu.r3h</a></td><td>FULL</td><td>ON</td><td>7</td><td>Feb 03 2003  01:59AM</td><td>INFLIGHT</td><td>11146</td><td>Feb 12 2003  09:53PM</td><td>2003/02/13 14:56:00 US/Eastern</td><td>Pipeline dark: 120 frame superdark with hotpixels from 03/02/2003</td></tr>
        <tr><td><a href="http://archive.stsci.edu/cgi-bin/dataset_lookup?dataset_input_list=n271647cu*">n271647cu.r3h</a></td><td>FULL</td><td>OFF</td><td>15</td><td>Feb 03 2003  01:59AM</td><td>INFLIGHT</td><td>11146</td><td>Feb 12 2003  09:53PM</td><td>2003/02/13 14:56:00 US/Eastern</td><td>Pipeline dark: 120 frame superdark with hotpixels from 03/02/2003</td></tr>
        <tr><td><a href="http://archive.stsci.edu/cgi-bin/dataset_lookup?dataset_input_list=n271647du*">n271647du.r3h</a></td><td>FULL</td><td>ON</td><td>15</td><td>Feb 03 2003  01:59AM</td><td>INFLIGHT</td><td>11146</td><td>Feb 12 2003  09:53PM</td><td>2003/02/13 14:56:00 US/Eastern</td><td>Pipeline dark: 120 frame superdark with hotpixels from 03/02/2003</td></tr>
        <tr><td><a href="http://archive.stsci.edu/cgi-bin/dataset_lookup?dataset_input_list=n271628hu*">n271628hu.r3h</a></td><td>FULL</td><td>OFF</td><td>7</td><td>Jan 27 2003  02:36AM</td><td>INFLIGHT</td><td>11143</td><td>Feb 10 2003  04:19PM</td><td>2003/02/11 17:53:00 US/Eastern</td><td>Pipeline dark: 120 frame superdark with hotpixels from 27/01/2003</td></tr>
        <tr><td><a href="http://archive.stsci.edu/cgi-bin/dataset_lookup?dataset_input_list=n271628iu*">n271628iu.r3h</a></td><td>FULL</td><td>ON</td><td>7</td><td>Jan 27 2003  02:36AM</td><td>INFLIGHT</td><td>11143</td><td>Feb 10 2003  04:19PM</td><td>2003/02/11 17:53:00 US/Eastern</td><td>Pipeline dark: 120 frame superdark with hotpixels from 27/01/2003</td></tr>
        <tr><td><a href="http://archive.stsci.edu/cgi-bin/dataset_lookup?dataset_input_list=n271628fu*">n271628fu.r3h</a></td><td>FULL</td><td>OFF</td><td>15</td><td>Jan 27 2003  02:36AM</td><td>INFLIGHT</td><td>11143</td><td>Feb 10 2003  04:19PM</td><td>2003/02/11 17:53:00 US/Eastern</td><td>Pipeline dark: 120 frame superdark with hotpixels from 27/01/2003</td></tr>
        <tr><td><a href="http://archive.stsci.edu/cgi-bin/dataset_lookup?dataset_input_list=n271628gu*">n271628gu.r3h</a></td><td>FULL</td><td>ON</td><td>15</td><td>Jan 27 2003  02:36AM</td><td>INFLIGHT</td><td>11143</td><td>Feb 10 2003  04:19PM</td><td>2003/02/11 17:53:00 US/Eastern</td><td>Pipeline dark: 120 frame superdark with hotpixels from 27/01/2003</td></tr>
        <tr><td><a href="http://archive.stsci.edu/cgi-bin/dataset_lookup?dataset_input_list=n1s1118ou*">n1s1118ou.r3h</a></td><td>FULL</td><td>OFF</td><td>7</td><td>Jan 24 2003  02:40PM</td><td>INFLIGHT</td><td>11136</td><td>Jan 28 2003  09:13PM</td><td>2003/01/29 14:08:00 US/Eastern</td><td>Pipeline dark: 120 frame superdark with hotpixels from 24/01/2003</td></tr>
        <tr><td><a href="http://archive.stsci.edu/cgi-bin/dataset_lookup?dataset_input_list=n1s1118pu*">n1s1118pu.r3h</a></td><td>FULL</td><td>ON</td><td>7</td><td>Jan 24 2003  02:40PM</td><td>INFLIGHT</td><td>11136</td><td>Jan 28 2003  09:13PM</td><td>2003/01/29 14:08:00 US/Eastern</td><td>Pipeline dark: 120 frame superdark with hotpixels from 24/01/2003</td></tr>
        <tr><td><a href="http://archive.stsci.edu/cgi-bin/dataset_lookup?dataset_input_list=n1s1118mu*">n1s1118mu.r3h</a></td><td>FULL</td><td>OFF</td><td>15</td><td>Jan 24 2003  02:40PM</td><td>INFLIGHT</td><td>11136</td><td>Jan 28 2003  09:13PM</td><td>2003/01/29 14:08:00 US/Eastern</td><td>Pipeline dark: 120 frame superdark with hotpixels from 24/01/2003</td></tr>
        <tr><td><a href="http://archive.stsci.edu/cgi-bin/dataset_lookup?dataset_input_list=n1s1118nu*">n1s1118nu.r3h</a></td><td>FULL</td><td>ON</td><td>15</td><td>Jan 24 2003  02:40PM</td><td>INFLIGHT</td><td>11136</td><td>Jan 28 2003  09:13PM</td><td>2003/01/29 14:08:00 US/Eastern</td><td>Pipeline dark: 120 frame superdark with hotpixels from 24/01/2003</td></tr>
        <tr><td><a href="http://archive.stsci.edu/cgi-bin/dataset_lookup?dataset_input_list=n1n1312tu*">n1n1312tu.r3h</a></td><td>FULL</td><td>OFF</td><td>7</td><td>Jan 20 2003  12:23PM</td><td>INFLIGHT</td><td>11135</td><td>Jan 27 2003  04:15PM</td><td>2003/01/27 17:02:00 US/Eastern</td><td>Pipeline dark: 120 frame superdark with hotpixels from 20/01/2003</td></tr>
        <tr><td><a href="http://archive.stsci.edu/cgi-bin/dataset_lookup?dataset_input_list=n1n13130u*">n1n13130u.r3h</a></td><td>FULL</td><td>ON</td><td>7</td><td>Jan 20 2003  12:23PM</td><td>INFLIGHT</td><td>11135</td><td>Jan 27 2003  04:15PM</td><td>2003/01/27 17:02:00 US/Eastern</td><td>Pipeline dark: 120 frame superdark with hotpixels from 20/01/2003</td></tr>
        <tr><td><a href="http://archive.stsci.edu/cgi-bin/dataset_lookup?dataset_input_list=n1n1312ru*">n1n1312ru.r3h</a></td><td>FULL</td><td>OFF</td><td>15</td><td>Jan 20 2003  12:23PM</td><td>INFLIGHT</td><td>11135</td><td>Jan 27 2003  04:15PM</td><td>2003/01/27 17:02:00 US/Eastern</td><td>Pipeline dark: 120 frame superdark with hotpixels from 20/01/2003</td></tr>
        <tr><td><a href="http://archive.stsci.edu/cgi-bin/dataset_lookup?dataset_input_list=n1n1312su*">n1n1312su.r3h</a></td><td>FULL</td><td>ON</td><td>15</td><td>Jan 20 2003  12:23PM</td><td>INFLIGHT</td><td>11135</td><td>Jan 27 2003  04:15PM</td><td>2003/01/27 17:02:00 US/Eastern</td><td>Pipeline dark: 120 frame superdark with hotpixels from 20/01/2003</td></tr>
        <tr><td><a href="http://archive.stsci.edu/cgi-bin/dataset_lookup?dataset_input_list=n1k1256hu*">n1k1256hu.r3h</a></td><td>FULL</td><td>OFF</td><td>7</td><td>Jan 13 2003  03:42AM</td><td>INFLIGHT</td><td>11133</td><td>Jan 21 2003  09:13PM</td><td>2003/01/21 22:22:00 US/Eastern</td><td>Pipeline dark: 120 frame superdark with hotpixels from 13/01/2003</td></tr>
        <tr><td><a href="http://archive.stsci.edu/cgi-bin/dataset_lookup?dataset_input_list=n1k1256iu*">n1k1256iu.r3h</a></td><td>FULL</td><td>ON</td><td>7</td><td>Jan 13 2003  03:42AM</td><td>INFLIGHT</td><td>11133</td><td>Jan 21 2003  09:13PM</td><td>2003/01/21 22:22:00 US/Eastern</td><td>Pipeline dark: 120 frame superdark with hotpixels from 13/01/2003</td></tr>
        <tr><td><a href="http://archive.stsci.edu/cgi-bin/dataset_lookup?dataset_input_list=n1k1256fu*">n1k1256fu.r3h</a></td><td>FULL</td><td>OFF</td><td>15</td><td>Jan 13 2003  03:42AM</td><td>INFLIGHT</td><td>11133</td><td>Jan 21 2003  09:13PM</td><td>2003/01/21 22:22:00 US/Eastern</td><td>Pipeline dark: 120 frame superdark with hotpixels from 13/01/2003</td></tr>
        <tr><td><a href="http://archive.stsci.edu/cgi-bin/dataset_lookup?dataset_input_list=n1k1256gu*">n1k1256gu.r3h</a></td><td>FULL</td><td>ON</td><td>15</td><td>Jan 13 2003  03:42AM</td><td>INFLIGHT</td><td>11133</td><td>Jan 21 2003  09:13PM</td><td>2003/01/21 22:22:00 US/Eastern</td><td>Pipeline dark: 120 frame superdark with hotpixels from 13/01/2003</td></tr>
        <tr><td><a href="http://archive.stsci.edu/cgi-bin/dataset_lookup?dataset_input_list=n1e16408u*">n1e16408u.r3h</a></td><td>FULL</td><td>OFF</td><td>7</td><td>Jan 06 2003  03:59AM</td><td>INFLIGHT</td><td>11128</td><td>Jan 16 2003  08:46PM</td><td>2003/01/16 22:42:00 US/Eastern</td><td>Pipeline dark: 120 frame superdark with hotpixels from 06/01/2003</td></tr>
        <tr><td><a href="http://archive.stsci.edu/cgi-bin/dataset_lookup?dataset_input_list=n1e16409u*">n1e16409u.r3h</a></td><td>FULL</td><td>ON</td><td>7</td><td>Jan 06 2003  03:59AM</td><td>INFLIGHT</td><td>11128</td><td>Jan 16 2003  08:46PM</td><td>2003/01/16 22:42:00 US/Eastern</td><td>Pipeline dark: 120 frame superdark with hotpixels from 06/01/2003</td></tr>
        <tr><td><a href="http://archive.stsci.edu/cgi-bin/dataset_lookup?dataset_input_list=n1e16406u*">n1e16406u.r3h</a></td><td>FULL</td><td>OFF</td><td>15</td><td>Jan 06 2003  03:59AM</td><td>INFLIGHT</td><td>11128</td><td>Jan 16 2003  08:46PM</td><td>2003/01/16 22:42:00 US/Eastern</td><td>Pipeline dark: 120 frame superdark with hotpixels from 06/01/2003</td></tr>
        <tr><td><a href="http://archive.stsci.edu/cgi-bin/dataset_lookup?dataset_input_list=n1e16407u*">n1e16407u.r3h</a></td><td>FULL</td><td>ON</td><td>15</td><td>Jan 06 2003  03:59AM</td><td>INFLIGHT</td><td>11128</td><td>Jan 16 2003  08:46PM</td><td>2003/01/16 22:42:00 US/Eastern</td><td>Pipeline dark: 120 frame superdark with hotpixels from 06/01/2003</td></tr>
    </table>
</document>