<document>
    <url>
        http://www.stsci.edu/hst/observatory/cdbs/SIfileInfo/WFPC2/reftablequeryindex_wfpc2/WFPC2Shading
    </url>
    <table>
        <tr><th>File</th><th>Mode</th><th>Shutter</th><th>Use After</th><th>Pedigree</th><th>Delivery #</th><th>Delivery Date</th><th>OTFR Start Date</th><th>Comments</th></tr>
        <tr><td><a href="http://archive.stsci.edu/cgi-bin/dataset_lookup?dataset_input_list=e1b10013u*">e1b10013u.r5h</a></td><td>AREA</td><td>A</td><td>Dec 01 1993  00:00:00 UT</td><td>DUMMY</td><td>2785</td><td>Jan 12 1994  11:14:27 GMT</td><td>1994/01/15 00:43:00 US/Eastern</td><td>use e6o09402u instead of this one; t. vac (grnd) test data; 2x2 blka</td></tr>
        <tr><td><a href="http://archive.stsci.edu/cgi-bin/dataset_lookup?dataset_input_list=e6o09402u*">e6o09402u.r5h</a></td><td>AREA</td><td>A</td><td>Apr 23 1994  00:00:00 UT</td><td>GROUND</td><td>3138</td><td>Jun 24 1994  11:24:22 GMT</td><td>1994/06/24 17:36:00 GMT-4</td><td>thermal vac (grnd) test data; 2x2 blkavg of e371355eu</td></tr>
        <tr><td><a href="http://archive.stsci.edu/cgi-bin/dataset_lookup?dataset_input_list=e371355eu*">e371355eu.r5h</a></td><td>FULL</td><td>A</td><td>Dec 01 1993  00:00:00 UT</td><td>GROUND</td><td>2835</td><td>Mar 07 1994  14:44:44 GMT</td><td>1994/03/07 22:00:00 US/Eastern</td><td>redelivery; thermal vac (grnd) test data; use instead of dbu14243u</td></tr>
        <tr><td><a href="http://archive.stsci.edu/cgi-bin/dataset_lookup?dataset_input_list=e1b10014u*">e1b10014u.r5h</a></td><td>AREA</td><td>B</td><td>Dec 01 1993  00:00:00 UT</td><td>DUMMY</td><td>2786</td><td>Jan 12 1994  11:14:27 GMT</td><td>1994/01/15 00:43:00 US/Eastern</td><td>use e6o09405u instead of this one; t. vac (grnd) test data; 2x2 blka</td></tr>
        <tr><td><a href="http://archive.stsci.edu/cgi-bin/dataset_lookup?dataset_input_list=e6o09405u*">e6o09405u.r5h</a></td><td>AREA</td><td>B</td><td>Apr 23 1994  00:00:00 UT</td><td>GROUND</td><td>3139</td><td>Jun 24 1994  11:24:22 GMT</td><td>1994/06/24 17:36:00 GMT-4</td><td>thermal vac (grnd) test data; 2x2 blkavg of e371355iu</td></tr>
        <tr><td><a href="http://archive.stsci.edu/cgi-bin/dataset_lookup?dataset_input_list=e371355iu*">e371355iu.r5h</a></td><td>FULL</td><td>B</td><td>Dec 01 1993  00:00:00 UT</td><td>GROUND</td><td>2836</td><td>Mar 07 1994  14:44:44 GMT</td><td>1994/03/07 22:00:00 US/Eastern</td><td>redelivery; thermal vac (grnd) test data; use instead of dbu14245u</td></tr>
    </table>
</document>